Workbook

Sheet A1 Income Statement
A2: Apple FY2026 Q4 Income Statement and EPS Forecast | H2: Assumptions and rationale
A3: USD millions, except per-share data
A4: Income statement | B4: FY2025 Q4 Actual | C4: FY2026 Q1 Actual | D4: FY2026 Q2 Actual | E4: FY2026 Q3 Actual | F4: FY2026 Q4 Forecast | H4: Driver | I4: Selected | J4: Benchmark or range | K4: Rationale | L4: Source
A5: Revenue and gross profit | H5: Net sales growth | I5: ='C1 Revenue Build'!C13 -> 0.10440556 | J5: Management guidance: 9%–11% YoY | K5: Bottom-up total from iPhone, Mac, iPad, Wearables and Services; the result remains within management's 9%-11% range. | L5: Apple FY2026 Q3 earnings call
A6: Products | B6: 73716 | C6: 113743 | D6: 80208 | E6: 78678 | F6: ='C1 Revenue Build'!D10 -> 80964.02 | H6: Services growth | I6: ='C1 Revenue Build'!C11 -> 0.12 | J6: Q3 growth adjusted for 2.5 ppt FX headwind | K6: Services uses the team's 12% base case; category-level assumptions are documented on C1 Revenue Build. | L6: Apple FY2026 Q3 earnings call
A7: Services | B7: 28750 | C7: 30013 | D7: 30976 | E7: 30739 | F7: ='C1 Revenue Build'!D11 -> 32200 | H7: Company gross margin | I7: 0.475 | J7: Management guidance: 47%–48% | K7: Midpoint incorporates higher memory costs, supply constraints and an expected tariff-refund benefit. | L7: Apple FY2026 Q3 earnings call
A8: Net sales | B8: 102466 | C8: 143756 | D8: 111184 | E8: 109417 | F8: ='C1 Revenue Build'!D12 -> 113164.02 | H8: Services gross margin | I8: 0.755 | J8: Near FY2026 Q3 actual: 75.6% | K8: Services margin has been stable near 75% recently; total margin guidance then implies the product margin. | L8: Company financials; Apple FY2026 Q3 results
A9: Product cost | B9: 47019 | C9: 67478 | D9: 49179 | E9: 47153 | F9: =F6-(F12-(F7-F10)) -> 51522.111 | H9: Total operating expenses | I9: 19250 | J9: Management guidance: $19.1–$19.4bn | K9: Midpoint of the company range; split between R&D and SG&A using the latest quarterly mix. | L9: Apple FY2026 Q3 earnings call
A10: Service cost | B10: 7106 | C10: 7047 | D10: 7224 | E10: 7494 | F10: =F7*(1-$I$8) -> 7889 | H10: R&D share of operating expenses | I10: 0.6148886 | J10: FY2026 Q3 R&D/Opex mix | K10: Uses the latest expense composition while preserving management’s total Opex guidance. | L10: Company financials
A11: Cost of sales | B11: 54125 | C11: 74525 | D11: 56403 | E11: 54647 | F11: =F9+F10 -> 59411.111 | H11: Other income/(expense), net | I11: 350 | J11: Management guidance: about $350m | K11: Uses the specific company outlook rather than a volatile historical average. | L11: Apple FY2026 Q3 earnings call
A12: Gross margin | B12: 48341 | C12: 69231 | D12: 54781 | E12: 54770 | F12: =F8*$I$7 -> 53752.91 | H12: Effective tax rate | I12: 0.165 | J12: Management guidance: about 16.5% | K12: Avoids the unusually high FY2024 Q4 tax rate caused by a one-off tax item. | L12: Apple FY2026 Q3 earnings call
A13: Gross margin % | B13: 0.471776 | C13: 0.48158686 | D13: 0.49270579 | E13: 0.50056207 | F13: =F12/F8 -> 0.475 | H13: Diluted weighted-average shares | I13: 14650 | J13: Recent decline and Q3 ending shares | K13: Assumes continued repurchases; Q4 average shares remain above the FY2026 Q3 ending balance. | L13: Company financials
A14: Product gross margin % | B14: 0.36216018 | C14: 0.40675031 | D14: 0.38685667 | E14: 0.4006838 | F14: =(F6-F9)/F6 -> 0.36364189
A15: Services gross margin % | B15: 0.75283478 | C15: 0.76520175 | D15: 0.76678719 | E15: 0.75620547 | F15: =(F7-F10)/F7 -> 0.755 | H15: Reference
H16: Apple Q3 results | I16: https://www.apple.com/newsroom/2026/07/apple-reports-third-quarter-results/
A17: Operating expenses | H17: Apple earnings call guidance | I17: https://www.fool.com/earnings/call-transcripts/2026/08/07/apple-aapl-q3-2026-earnings-call-transcript/
A18: Research and development | B18: 8866 | C18: 10887 | D18: 11419 | E18: 11729 | F18: =F20*$I$10 -> 11836.605 | H18: SEC Form 10-Q | I18: https://www.sec.gov/Archives/edgar/data/320193/000032019326000020/aapl-20260627.htm
A19: Selling, general and administrative | B19: 7048 | C19: 7492 | D19: 7477 | E19: 7346 | F19: =F20-F18 -> 7413.3945
A20: Total operating expenses | B20: 15914 | C20: 18379 | D20: 18896 | E20: 19075 | F20: =$I$9 -> 19250
A21: Operating income | B21: 32427 | C21: 50852 | D21: 35885 | E21: 35695 | F21: =F12-F20 -> 34502.91
A22: Operating margin % | B22: 0.31646595 | C22: 0.35373828 | D22: 0.32275327 | E22: 0.32622901 | F22: =F21/F8 -> 0.30489293
A24: Earnings and EPS
A25: Other income/(expense), net | B25: 377 | C25: 150 | D25: -52 | E25: 572 | F25: =$I$11 -> 350
A26: Income before provision for income taxes | B26: 32804 | C26: 51002 | D26: 35833 | E26: 36267 | F26: =F21+F25 -> 34852.91
A27: Effective tax rate | B27: 0.16272406 | C27: 0.174601 | D27: 0.17455976 | E27: 0.17861968 | F27: =$I$12 -> 0.165
A28: Provision for income taxes | B28: 5338 | C28: 8905 | D28: 6255 | E28: 6478 | F28: =F26*F27 -> 5750.7301
A29: Net income | B29: 27466 | C29: 42097 | D29: 29578 | E29: 29789 | F29: =F26-F28 -> 29102.179
A30: Diluted weighted-average shares | B30: 14863.61 | C30: 14810.36 | D30: 14725.87 | E30: 14714.68 | F30: =$I$13 -> 14650
A31: Diluted EPS | B31: 1.85 | C31: 2.84 | D31: 2.01 | E31: 2.02 | F31: =F29/F30 -> 1.9864969
A33: EPS formula check | B33: 0.002131279 | C33: -0.0024022103 | D33: 0.0014259735 | E33: -0.0044408985 | F33: =F31-(F29/F30) -> 0

Sheet A2 Q4 Drivers
A2: Income Statement Inputs and Forecast Drivers
A3: USD millions; EPS in USD per share; diluted shares in millions
A5: Item | B5: FY2025 Q4 Actual | C5: FY2026 Q3 Actual | D5: FY2026 Q4 Forecast Input | E5: Notes
A6: Quarterly income statement
A7: Net sales | B7: 102466 | C7: 109417 | D7: ='A1 Income Statement'!F8 -> 113164.02 | E7: Linked to A1 Income Statement forecast.
A8: Cost of sales | B8: 54125 | C8: 54647 | D8: ='A1 Income Statement'!F11 -> 59411.111 | E8: Linked to A1 Income Statement forecast.
A9: Operating income | B9: 32427 | C9: 35695 | D9: ='A1 Income Statement'!F21 -> 34502.91 | E9: Linked to A1 Income Statement forecast.
A10: Net income | B10: 27466 | C10: 29789 | D10: ='A1 Income Statement'!F29 -> 29102.179 | E10: Linked to A1 Income Statement forecast.
A11: Diluted EPS | B11: 1.85 | C11: 2.02 | D11: ='A1 Income Statement'!F31 -> 1.9864969 | E11: Linked to A1 Income Statement forecast.
A12: Diluted weighted-average shares (millions) | B12: 14863.609 | C12: 14714.676 | D12: ='A1 Income Statement'!F30 -> 14650 | E12: Linked to A1 Income Statement forecast.
A14: Quarter-end turnover and selected forecast ratios
A15: A/R turnover (revenue / ending A/R) | B15: =B7/'B Balance Sheet'!B9 -> 2.5760113 | C15: =C7/'B Balance Sheet'!C9 -> 3.4848398 | D15: =B15 -> 2.5760113 | E15: FY2025 Q4 ratio captures September-quarter receivables seasonality.
A16: Vendor receivables turnover (cost / ending balance) | B16: =B8/'B Balance Sheet'!B10 -> 1.6312538 | C16: =C8/'B Balance Sheet'!C10 -> 1.9865135 | D16: =B16 -> 1.6312538 | E16: FY2025 Q4 ratio captures September-quarter vendor settlements.
A17: Inventory turnover (cost / ending inventory) | B17: =B8/'B Balance Sheet'!B11 -> 9.4657223 | C17: =C8/'B Balance Sheet'!C11 -> 4.9267039 | D17: =C17 -> 4.9267039 | E17: Uses FY2026 Q3 turnover: inventory doubled versus FY2025 Q4, so a rapid return to the old level lacks support.
A18: A/P turnover (cost / ending A/P) | B18: =B8/'B Balance Sheet'!B24 -> 0.77476381 | C18: =C8/'B Balance Sheet'!C24 -> 0.84691205 | D18: =B18 -> 0.77476381 | E18: FY2025 Q4 ratio captures September-quarter supplier payment seasonality.
A19: Revenue / ending deferred revenue | B19: =B7/'B Balance Sheet'!B26 -> 11.315958 | C19: =C7/'B Balance Sheet'!C26 -> 11.471692 | D19: =B19 -> 11.315958 | E19: FY2025 Q4 ratio anchors ending deferred revenue to same-quarter sales.
A21: FY2026 Q4 equity adjustments
A22: Dividends and equivalents (positive outflow) | B22: 3888 | C22: 3998 | D22: =C22 -> 3998 | E22: Declared dividends and equivalents; Q3 run rate is the provisional Q4 assumption.
A23: Share repurchases (positive outflow) | B23: 20178 | C23: 25949 | D23: =C23 -> 25949 | E23: Recognized share repurchases in equity; Q3 run rate is the provisional Q4 assumption.
A24: Other retained earnings adjustment (signed) | B24: -57 | C24: -875 | D24: =C24 -> -875 | E24: Withheld equity awards charged to retained earnings; Q3 signed amount is carried forward.
A25: Common stock / APIC net change | B25: 3762 | C25: 1195 | D25: =C25 -> 1195 | E25: Q3 APIC increase = 3,591 share compensation - 2,396 withheld shares; carry forward one quarter.
A27: EPS comparison with two sell-side analysts
A28: Group FY2026 Q4 EPS | D28: =IF(COUNT(D11)<1,"",D11) -> 1.9864969 | E28: Group EPS is linked to A forecast; consensus is shown below for context only.
A29: Analyst 1 EPS | D29: 2.03 | E29: Chang, Rob from KGI Greater China
A30: Analyst 2 EPS | D30: 2.05 | E30: White, Brian J from Monness, Crespi, Hardt, & Co Inc.
A31: Group less Analyst 1 | D31: =D28-D29 -> -0.04350311
A32: Group less Analyst 2 | D32: =D28-D30 -> -0.06350311
A33: Market consensus EPS (context only) | D33: 1.98 | E33: LSEG Stock Report, 2 Oct 2026, p. 4: I/B/E/S mean 1.983 for quarter ending Sep 2026 (25 analysts; high 2.07, low 1.93). Cross-check: Yahoo Finance consensus 1.98, accessed 2026-10-05, https://finance.yahoo.com/quote/AAPL/analysis/. Consensus is not an individual analyst.
A34: Data sources
A35: FY2025 full year | B35: Apple FY2025 Form 10-K, PDF p. 32
A36: FY2025 first nine months | B36: Apple FY2026 Q3 Form 10-Q, PDF p. 4, 2025 nine-month comparative
A37: FY2025 Q4 EPS and shares | B37: Apple FY2025 Q4 Consolidated Financial Statements, PDF p. 1
A38: FY2026 Q3 Actual | B38: Apple FY2026 Q3 Form 10-Q, PDF p. 4, 2026 three-month actual
A39: Q4 net sales check | B39: =416161-313695 -> 102466 | E39: FY2025 full year 416,161 - first nine months 313,695 = 102,466
A40: Q4 cost of sales check | B40: =220960-166835 -> 54125 | E40: FY2025 full year 220,960 - first nine months 166,835 = 54,125
A41: FY2026 Q4 draft forecast | B41: A1 Income Statement tab, copied from AAPL_FY2026_Q4_IS_Forecast_Draft.xlsx, IS Forecast
A43: Forecast method rationale
A44: A/R, vendor receivables, A/P, deferred revenue | E44: Use FY2025 Q4 ending turnover with A's Q4 sales or cost of sales to capture same-season working capital.
A45: Inventory | E45: Use FY2026 Q3 ending turnover because the current inventory balance is unusually elevated; historical Q4 ratio would force an unsupported sharp reduction.
A46: Other balance-sheet lines | E46: Carry FY2026 Q3 balances forward where no standalone Q4 debt, capex, or OCI forecast is available; these are provisional assumptions.
A47: Equity movements | E47: Carry FY2026 Q3 declared dividends, recognized repurchases, RSU adjustment, and net APIC movement; all are linked to the equity statement.
A48: Cash plug | E48: Solve cash as total liabilities and equity less all other forecast assets; zero difference is an accounting identity, not cash-flow validation.
A49: Income statement link | E49: B drivers link to the copied A forecast formulas, so edits to A assumptions recalculate B revenue, cost, net income, EPS, and balance sheet.

Sheet B Balance Sheet
A2: Apple Balance Sheet Forecast
A3: USD millions; FY2025 Q4 and FY2026 Q3 are actual quarter-end balances
A5: Balance sheet item | B5: FY2025 Q4 Actual | C5: FY2026 Q3 Actual | D5: FY2026 Q4 Forecast | E5: Forecast method / follow-up
A6: Current assets
A7: Cash and cash equivalents | B7: 35934 | C7: 39544 | D7: =IF(OR(COUNT(D40)<1,COUNT(D8:D12,D16:D19)<9),"",D40-SUM(D8:D12,D16:D19)) -> 29228.981 | E7: Residual cash after forecasting other assets, liabilities, and equity; check versus Q3 balance.
A8: Current marketable securities | B8: 18763 | C8: 22855 | D8: =C8 -> 22855 | E8: Carry forward FY2026 Q3; revise if separately forecast
A9: Accounts receivable, net | B9: 39777 | C9: 31398 | D9: =IF(COUNT('A2 Q4 Drivers'!D7,'A2 Q4 Drivers'!D15)<2,"",'A2 Q4 Drivers'!D7/'A2 Q4 Drivers'!D15) -> 43929.94 | E9: Q4 revenue / selected A/R turnover
A10: Vendor non-trade receivables | B10: 33180 | C10: 27509 | D10: =IF(COUNT('A2 Q4 Drivers'!D8,'A2 Q4 Drivers'!D16)<2,"",'A2 Q4 Drivers'!D8/'A2 Q4 Drivers'!D16) -> 36420.52 | E10: Q4 cost of sales / selected turnover
A11: Inventories | B11: 5718 | C11: 11092 | D11: =IF(COUNT('A2 Q4 Drivers'!D8,'A2 Q4 Drivers'!D17)<2,"",'A2 Q4 Drivers'!D8/'A2 Q4 Drivers'!D17) -> 12058.998 | E11: Q4 cost of sales / FY2026 Q3 inventory turnover; retains elevated 2026 inventory level.
A12: Other current assets | B12: 14585 | C12: 17420 | D12: =C12 -> 17420 | E12: Carry forward FY2026 Q3
A13: Total current assets | B13: =SUM(B7:B12) -> 147957 | C13: =SUM(C7:C12) -> 149818 | D13: =IF(COUNT(D7:D12)<6,"",SUM(D7:D12)) -> 161913.44 | E13: Formula total
A15: Non-current assets
A16: Non-current marketable securities | B16: 77723 | C16: 84118 | D16: =C16 -> 84118 | E16: Carry forward FY2026 Q3
A17: Property, plant and equipment, net | B17: 49834 | C17: 51431 | D17: =C17 -> 51431 | E17: Carry forward FY2026 Q3; update for capex and depreciation
A18: Non-current intangible assets, net | B18: 11093 | C18: 20342 | D18: =C18 -> 20342 | E18: Carry forward FY2026 Q3; FY2025 comparative is reclassified
A19: Other non-current assets | B19: 72634 | C19: 77557 | D19: =C19 -> 77557 | E19: Carry forward FY2026 Q3
A20: Total non-current assets | B20: =SUM(B16:B19) -> 211284 | C20: =SUM(C16:C19) -> 233448 | D20: =IF(COUNT(D16:D19)<4,"",SUM(D16:D19)) -> 233448 | E20: Formula total
A21: Total assets | B21: =B13+B20 -> 359241 | C21: =C13+C20 -> 383266 | D21: =IF(COUNT(D13,D20)<2,"",D13+D20) -> 395361.44 | E21: Formula total
A23: Current liabilities
A24: Accounts payable | B24: 69860 | C24: 64525 | D24: =IF(COUNT('A2 Q4 Drivers'!D8,'A2 Q4 Drivers'!D18)<2,"",'A2 Q4 Drivers'!D8/'A2 Q4 Drivers'!D18) -> 76682.867 | E24: Q4 cost of sales / selected A/P turnover
A25: Other current liabilities | B25: 66387 | C25: 62259 | D25: =C25 -> 62259 | E25: Carry forward FY2026 Q3
A26: Deferred revenue | B26: 9055 | C26: 9538 | D26: =IF(COUNT('A2 Q4 Drivers'!D7,'A2 Q4 Drivers'!D19)<2,"",'A2 Q4 Drivers'!D7/'A2 Q4 Drivers'!D19) -> 10000.392 | E26: Q4 revenue / selected revenue-to-deferred-revenue ratio
A27: Commercial paper | B27: 7979 | C27: 1997 | D27: =C27 -> 1997 | E27: Carry forward FY2026 Q3; review issuance and maturities
A28: Current term debt | B28: 12350 | C28: 11007 | D28: =C28 -> 11007 | E28: Carry forward FY2026 Q3; review maturities
A29: Total current liabilities | B29: =SUM(B24:B28) -> 165631 | C29: =SUM(C24:C28) -> 149326 | D29: =IF(COUNT(D24:D28)<5,"",SUM(D24:D28)) -> 161946.26 | E29: Formula total
A30: Non-current liabilities
A31: Long-term debt | B31: 78328 | C31: 71340 | D31: =C31 -> 71340 | E31: Carry forward FY2026 Q3; review maturities
A32: Other non-current liabilities | B32: 41549 | C32: 55080 | D32: =C32 -> 55080 | E32: Carry forward FY2026 Q3
A33: Total non-current liabilities | B33: =SUM(B31:B32) -> 119877 | C33: =SUM(C31:C32) -> 126420 | D33: =IF(COUNT(D31:D32)<2,"",SUM(D31:D32)) -> 126420 | E33: Formula total
A34: Total liabilities | B34: =B29+B33 -> 285508 | C34: =C29+C33 -> 275746 | D34: =IF(COUNT(D29,D33)<2,"",D29+D33) -> 288366.26 | E34: Formula total
A35: Shareholders' equity
A36: Common stock and additional paid-in capital | B36: 93568 | C36: 100702 | D36: =IF(COUNT('A2 Q4 Drivers'!D25)<1,"",C36+'A2 Q4 Drivers'!D25) -> 101897 | E36: FY2026 Q3 APIC plus Q3 net APIC movement; linked to A2 Q4 Drivers.
A37: Retained earnings / accumulated deficit | B37: -14264 | C37: 11326 | D37: =IF(COUNT('A2 Q4 Drivers'!D10,'A2 Q4 Drivers'!D22,'A2 Q4 Drivers'!D23,'A2 Q4 Drivers'!D24)<4,"",C37+'A2 Q4 Drivers'!D10-'A2 Q4 Drivers'!D22-'A2 Q4 Drivers'!D23+'A2 Q4 Drivers'!D24) -> 9606.1794 | E37: Q3 retained earnings + A net income - declared dividends - recognized buybacks + RSU adjustment.
A38: Accumulated other comprehensive loss | B38: -5571 | C38: -4508 | D38: =C38 -> -4508 | E38: Carry forward FY2026 Q3
A39: Total shareholders' equity | B39: =SUM(B36:B38) -> 73733 | C39: =SUM(C36:C38) -> 107520 | D39: =IF(COUNT(D36:D38)<3,"",SUM(D36:D38)) -> 106995.18 | E39: Formula total
A40: Total liabilities and shareholders' equity | B40: =B34+B39 -> 359241 | C40: =C34+C39 -> 383266 | D40: =IF(COUNT(D34,D39)<2,"",D34+D39) -> 395361.44 | E40: Formula total
A42: Balance sheet difference | B42: =B21-B40 -> 0 | C42: =C21-C40 -> 0 | D42: =IF(COUNT(D21,D40)<2,"",ROUND(D21-D40,2)) -> 0
A43: Forecast status | D43: =IF(COUNT('A2 Q4 Drivers'!D7,'A2 Q4 Drivers'!D8,'A2 Q4 Drivers'!D10)<3,"Awaiting Q4 income forecast",IF(COUNT('A2 Q4 Drivers'!D22:D25)<4,"Awaiting equity assumptions",IF(COUNT(D42)<1,"Forecast incomplete",IF(D7<0,"Negative cash: review assumptions",IF(ABS(D42)>0.005,"Out of balance","Balanced (cash plug)"))))) -> Balanced (cash plug)
A44: Cash change vs FY2026 Q3 | D44: =IF(COUNT(D7,C7)<2,"",D7-C7) -> -10315.019
A46: Sources and basis
A47: FY2025 Q4 Actual | B47: Apple FY2025 Form 10-K, PDF p. 34 (2025-09-27)
A48: FY2026 Q3 Actual | B48: Apple FY2026 Q3 Form 10-Q, PDF p. 6 (2026-06-27)
A49: Intangible assets reclassification | B49: FY2026 Q3 Form 10-Q, PDF pp. 6, 13: FY2025 non-current intangibles 11,093 + other non-current assets 72,634 = 83,727
A50: Forecast note | B50: Q3 carry-forward amounts are starting assumptions. Editable inputs are yellow on A2 Q4 Drivers. Review the cash plug separately.
A51: Equity assumptions | B51: FY2026 Q3 Form 10-Q, PDF p. 7, shareholders equity statement; FY2025 Q4 benchmark = FY2025 10-K p. 35 less nine months.

Sheet C1 Revenue Build
A1: Apple Segmented Revenue Forecast Build
A2: USD millions; yellow cells are editable assumptions. FY2026 Q4 is built bottom-up by product category, then flows into the annual income statement and valuation.
A4: FY2026 Q4 bottom-up revenue build
A5: Category | B5: FY2025 Q4 Actual | C5: Q4 Growth Assumption | D5: FY2026 Q4 Forecast | E5: FY2026 Q1-Q3 Actual | F5: FY2026 Annual Forecast | G5: Basis / rationale | H5: Primary source
A6: iPhone | B6: 49025 | C6: 0.14 | D6: =B6*(1+C6) -> 55888.5 | E6: 196515 | F6: =D6+E6 -> 252403.5 | G6: Management outlook: reported growth in the mid-teens; use the low end of the range. | H6: Apple FY2026 Q3 results / earnings call
A7: Mac | B7: 8726 | C7: 0.06 | D7: =B7*(1+C7) -> 9249.56 | E7: 27137 | F7: =D7+E7 -> 36386.56 | G7: Positive demand momentum, moderated for supply constraints. | H7: Apple FY2026 Q3 results / earnings call
A8: iPad | B8: 6952 | C8: -0.02 | D8: =B8*(1+C8) -> 6812.96 | E8: 21700 | F8: =D8+E8 -> 28512.96 | G8: Recent weakness and supply constraints support a slightly negative base case. | H8: Apple FY2026 Q3 results / earnings call
A9: Wearables, Home and Accessories | B9: 9013 | C9: 0 | D9: =B9*(1+C9) -> 9013 | E9: 27277 | F9: =D9+E9 -> 36290 | G9: Use a flat base case after a broadly stable recent quarter. | H9: Apple FY2026 Q3 results / earnings call
A10: Products total | B10: =SUM(B6:B9) -> 73716 | C10: =D10/B10-1 -> 0.098323566 | D10: =SUM(D6:D9) -> 80964.02 | E10: =SUM(E6:E9) -> 272629 | F10: =SUM(F6:F9) -> 353593.02 | G10: Derived from the four product categories above. | H10: Formula-derived
A11: Services | B11: 28750 | C11: 0.12 | D11: =B11*(1+C11) -> 32200 | E11: 91728 | F11: =D11+E11 -> 123928 | G11: Strong double-digit structural growth; team-selected base case. | H11: Apple FY2026 Q3 results / team assumption
A12: Net sales | B12: =B10+B11 -> 102466 | C12: =D12/B12-1 -> 0.10440556 | D12: =D10+D11 -> 113164.02 | E12: =E10+E11 -> 364357 | F12: =F10+F11 -> 477521.02 | G12: Bottom-up total; used as the Q4 revenue forecast. | H12: Formula-derived
A13: Management guidance check | B13: 9.0% to 11.0% | C13: =C12 -> 0.10440556 | D13: =IF(AND(C13>=9%,C13<=11%),"Within guidance",IF(C13<9%,"Below guidance","Above guidance")) -> Within guidance | G13: Apple guided September-quarter total revenue growth to 9%-11% year over year. | H13: Apple FY2026 Q3 earnings call
A16: Annual revenue forecast by category
A17: Category | B17: FY2026 | C17: FY2027 | D17: FY2028 | E17: FY2029 | F17: FY2030 | G17: FY2031 | H17: FY2032
A18: iPhone | B18: =F6 -> 252403.5 | C18: =B18*(1+$B$29) -> 272595.78 | D18: =C18*(1+$C$29) -> 290314.51 | E18: =D18*(1+$D$29) -> 306281.8 | F18: =E18*(1+$E$29) -> 321595.89 | G18: =F18*(1+$F$29) -> 336067.71 | H18: =G18*(1+$G$29) -> 349510.42
A19: Mac | B19: =F7 -> 36386.56 | C19: =B19*(1+$B$30) -> 38569.754 | D19: =C19*(1+$C$30) -> 40498.241 | E19: =D19*(1+$D$30) -> 42320.662 | F19: =E19*(1+$E$30) -> 44013.489 | G19: =F19*(1+$F$30) -> 45553.961 | H19: =G19*(1+$G$30) -> 46920.58
A20: iPad | B20: =F8 -> 28512.96 | C20: =B20*(1+$B$31) -> 29368.349 | D20: =C20*(1+$C$31) -> 30249.399 | E20: =D20*(1+$D$31) -> 31156.881 | F20: =E20*(1+$E$31) -> 31935.803 | G20: =F20*(1+$F$31) -> 32734.198 | H20: =G20*(1+$G$31) -> 33388.882
A21: Wearables, Home and Accessories | B21: =F9 -> 36290 | C21: =B21*(1+$B$32) -> 38104.5 | D21: =C21*(1+$C$32) -> 39819.202 | E21: =D21*(1+$D$32) -> 41411.971 | F21: =E21*(1+$E$32) -> 42861.39 | G21: =F21*(1+$F$32) -> 44361.538 | H21: =G21*(1+$G$32) -> 45692.384
A22: Services | B22: =F11 -> 123928 | C22: =B22*(1+$B$33) -> 138799.36 | D22: =C22*(1+$C$33) -> 154067.29 | E22: =D22*(1+$D$33) -> 169474.02 | F22: =E22*(1+$E$33) -> 184726.68 | G22: =F22*(1+$F$33) -> 199504.81 | H22: =G22*(1+$G$33) -> 213470.15
A23: Products total | B23: =SUM(B18:B21) -> 353593.02 | C23: =SUM(C18:C21) -> 378638.38 | D23: =SUM(D18:D21) -> 400881.35 | E23: =SUM(E18:E21) -> 421171.32 | F23: =SUM(F18:F21) -> 440406.58 | G23: =SUM(G18:G21) -> 458717.41 | H23: =SUM(H18:H21) -> 475512.26
A24: Net sales | B24: =B23+B22 -> 477521.02 | C24: =C23+C22 -> 517437.74 | D24: =D23+D22 -> 554948.64 | E24: =E23+E22 -> 590645.34 | F24: =F23+F22 -> 625133.26 | G24: =G23+G22 -> 658222.22 | H24: =H23+H22 -> 688982.42
A25: Net sales growth | B25: =B24/416161-1 -> 0.14744298 | C25: =C24/B24-1 -> 0.08359155 | D25: =D24/C24-1 -> 0.072493544 | E25: =E24/D24-1 -> 0.064324327 | F25: =F24/E24-1 -> 0.058390234 | G25: =G24/F24-1 -> 0.052931059 | H25: =H24/G24-1 -> 0.046732233
A27: Detailed annual growth assumptions
A28: Category | B28: FY2027 | C28: FY2028 | D28: FY2029 | E28: FY2030 | F28: FY2031 | G28: FY2032 | H28: Rationale
A29: iPhone | B29: 0.08 | C29: 0.065 | D29: 0.055 | E29: 0.05 | F29: 0.045 | G29: 0.04 | H29: Largest product line; normalize gradually after a strong FY2026 cycle.
A30: Mac | B30: 0.06 | C30: 0.05 | D30: 0.045 | E30: 0.04 | F30: 0.035 | G30: 0.03 | H30: Moderate growth with a mature installed base and normal product cycles.
A31: iPad | B31: 0.03 | C31: 0.03 | D31: 0.03 | E31: 0.025 | F31: 0.025 | G31: 0.02 | H31: Conservative growth after a softer FY2026 Q4 base case.
A32: Wearables, Home and Accessories | B32: 0.05 | C32: 0.045 | D32: 0.04 | E32: 0.035 | F32: 0.035 | G32: 0.03 | H32: Return to modest growth, then converge toward a mature profile.
A33: Services | B33: 0.12 | C33: 0.11 | D33: 0.1 | E33: 0.09 | F33: 0.08 | G33: 0.07 | H33: Remain faster-growing than Products, with gradual deceleration as the base expands.
A36: Source references and model controls
A37: Apple FY2026 Q1 consolidated financial statements | B37: https://www.apple.com/newsroom/pdfs/fy2026-q1/FY26_Q1_Consolidated_Financial_Statements.pdf
A38: Apple FY2026 Q2 consolidated financial statements | B38: https://www.apple.com/newsroom/pdfs/fy2026-q2/FY26_Q2_Consolidated_Financial_Statements.pdf
A39: Apple FY2026 Q3 consolidated financial statements | B39: https://www.apple.com/newsroom/pdfs/fy2026-q3/FY26_Q3_Consolidated_Financial_Statements.pdf
A40: Apple FY2026 Q3 earnings call transcript | B40: https://www.fool.com/earnings/call-transcripts/2026/08/07/apple-aapl-q3-2026-earnings-call-transcript/
A41: Apple FY2026 Q3 Form 10-Q | B41: https://www.sec.gov/Archives/edgar/data/320193/000032019326000020/aapl-20260627.htm
A43: Control: category FY2026 revenue less annual IS revenue | B43: ='C1 Revenue Build'!B24-'C2 Annual IS Forecast'!G9 -> 0
A44: Control: segmented FY2026 Products less annual IS Products | B44: ='C1 Revenue Build'!B23-'C2 Annual IS Forecast'!G7 -> 0
C49: Category | D49: FY2025 Q4 actual | E49: Growth assumption | F49: FY2026 Q4 forecast
C50: iPhone | D50: =B6/1000 -> 49.025 | E50: =C6 -> 0.14 | F50: =D6/1000 -> 55.8885
C51: Mac | D51: =B7/1000 -> 8.726 | E51: =C7 -> 0.06 | F51: =D7/1000 -> 9.24956
C52: iPad | D52: =B8/1000 -> 6.952 | E52: =C8 -> -0.02 | F52: =D8/1000 -> 6.81296
C53: Wearables | D53: =B9/1000 -> 9.013 | E53: =C9 -> 0 | F53: =D9/1000 -> 9.013
C54: Services | D54: =B11/1000 -> 28.75 | E54: =C11 -> 0.12 | F54: =D11/1000 -> 32.2
C55: Total revenue | D55: =B12/1000 -> 102.466 | E55: =C12 -> 0.10440556 | F55: =D12/1000 -> 113.16402
C60: Fiscal year | D60: Total sales growth | E60: Products growth | F60: Services growth
C61: FY27 | D61: =C25 -> 0.08359155 | E61: =C23/B23-1 -> 0.070831043 | F61: =C22/B22-1 -> 0.12
C62: FY28 | D62: =D25 -> 0.072493544 | E62: =D23/C23-1 -> 0.058744616 | F62: =D22/C22-1 -> 0.11
C63: FY29 | D63: =E25 -> 0.064324327 | E63: =E23/D23-1 -> 0.050613402 | F63: =E22/D22-1 -> 0.1
C64: FY30 | D64: =F25 -> 0.058390234 | E64: =F23/E23-1 -> 0.045670863 | F64: =F22/E22-1 -> 0.09
C65: FY31 | D65: =G25 -> 0.052931059 | E65: =G23/F23-1 -> 0.041577106 | F65: =G22/F22-1 -> 0.08
C66: FY32 | D66: =H25 -> 0.046732233 | E66: =H23/G23-1 -> 0.036612644 | F66: =H22/G22-1 -> 0.07

Sheet C2 Annual IS Forecast
A2: Apple Annual Income Statement Forecast
A3: USD millions, except per-share data; FY2026 combines Q1-Q3 actuals with a bottom-up Q4 category forecast. FY2027-FY2032 Products and Services totals are driven by C1 Revenue Build.
A5: Income statement item | B5: FY2025 Actual | C5: FY2026 Q1 Actual | D5: FY2026 Q2 Actual | E5: FY2026 Q3 Actual | F5: FY2026 Q4 Forecast | G5: FY2026 Annual Forecast | H5: FY2027 Forecast | I5: FY2028 Forecast | J5: FY2029 Forecast | K5: FY2030 Forecast | L5: FY2031 Forecast | M5: FY2032 Forecast
A6: Revenue and gross profit
A7: Products | B7: 307003 | C7: ='A1 Income Statement'!C6 -> 113743 | D7: ='A1 Income Statement'!D6 -> 80208 | E7: ='A1 Income Statement'!E6 -> 78678 | F7: ='A1 Income Statement'!F6 -> 80964.02 | G7: ='C1 Revenue Build'!B23 -> 353593.02 | H7: ='C1 Revenue Build'!C23 -> 378638.38 | I7: ='C1 Revenue Build'!D23 -> 400881.35 | J7: ='C1 Revenue Build'!E23 -> 421171.32 | K7: ='C1 Revenue Build'!F23 -> 440406.58 | L7: ='C1 Revenue Build'!G23 -> 458717.41 | M7: ='C1 Revenue Build'!H23 -> 475512.26
A8: Services | B8: 109158 | C8: ='A1 Income Statement'!C7 -> 30013 | D8: ='A1 Income Statement'!D7 -> 30976 | E8: ='A1 Income Statement'!E7 -> 30739 | F8: ='A1 Income Statement'!F7 -> 32200 | G8: ='C1 Revenue Build'!B22 -> 123928 | H8: ='C1 Revenue Build'!C22 -> 138799.36 | I8: ='C1 Revenue Build'!D22 -> 154067.29 | J8: ='C1 Revenue Build'!E22 -> 169474.02 | K8: ='C1 Revenue Build'!F22 -> 184726.68 | L8: ='C1 Revenue Build'!G22 -> 199504.81 | M8: ='C1 Revenue Build'!H22 -> 213470.15
A9: Net sales | B9: 416161 | C9: ='A1 Income Statement'!C8 -> 143756 | D9: ='A1 Income Statement'!D8 -> 111184 | E9: ='A1 Income Statement'!E8 -> 109417 | F9: ='A1 Income Statement'!F8 -> 113164.02 | G9: =SUM(C9:F9) -> 477521.02 | H9: =H7+H8 -> 517437.74 | I9: =I7+I8 -> 554948.64 | J9: =J7+J8 -> 590645.34 | K9: =K7+K8 -> 625133.26 | L9: =L7+L8 -> 658222.22 | M9: =M7+M8 -> 688982.42
A10: Product cost | B10: 194116 | C10: ='A1 Income Statement'!C9 -> 67478 | D10: ='A1 Income Statement'!D9 -> 49179 | E10: ='A1 Income Statement'!E9 -> 47153 | F10: ='A1 Income Statement'!F9 -> 51522.111 | G10: =SUM(C10:F10) -> 215332.11 | H10: =H7*(1-'D IS Assumptions'!D12) -> 229454.86 | I10: =I7*(1-'D IS Assumptions'!D13) -> 242132.33 | J10: =J7*(1-'D IS Assumptions'!D14) -> 253545.13 | K10: =K7*(1-'D IS Assumptions'!D15) -> 264243.95 | L10: =L7*(1-'D IS Assumptions'!D16) -> 274313.01 | M10: =M7*(1-'D IS Assumptions'!D17) -> 283405.31
A11: Service cost | B11: 26844 | C11: ='A1 Income Statement'!C10 -> 7047 | D11: ='A1 Income Statement'!D10 -> 7224 | E11: ='A1 Income Statement'!E10 -> 7494 | F11: ='A1 Income Statement'!F10 -> 7889 | G11: =SUM(C11:F11) -> 29654 | H11: =H8*(1-'D IS Assumptions'!E12) -> 33173.047 | I11: =I8*(1-'D IS Assumptions'!E13) -> 36668.015 | J11: =J8*(1-'D IS Assumptions'!E14) -> 40165.342 | K11: =K8*(1-'D IS Assumptions'!E15) -> 43595.497 | L11: =L8*(1-'D IS Assumptions'!E16) -> 46883.631 | M11: =M8*(1-'D IS Assumptions'!E17) -> 50165.486
A12: Cost of sales | B12: 220960 | C12: ='A1 Income Statement'!C11 -> 74525 | D12: ='A1 Income Statement'!D11 -> 56403 | E12: ='A1 Income Statement'!E11 -> 54647 | F12: ='A1 Income Statement'!F11 -> 59411.111 | G12: =SUM(C12:F12) -> 244986.11 | H12: =H10+H11 -> 262627.91 | I12: =I10+I11 -> 278800.35 | J12: =J10+J11 -> 293710.48 | K12: =K10+K11 -> 307839.44 | L12: =L10+L11 -> 321196.64 | M12: =M10+M11 -> 333570.79
A13: Gross margin | B13: 195201 | C13: ='A1 Income Statement'!C12 -> 69231 | D13: ='A1 Income Statement'!D12 -> 54781 | E13: ='A1 Income Statement'!E12 -> 54770 | F13: ='A1 Income Statement'!F12 -> 53752.91 | G13: =SUM(C13:F13) -> 232534.91 | H13: =H9-H12 -> 254809.84 | I13: =I9-I12 -> 276148.29 | J13: =J9-J12 -> 296934.86 | K13: =K9-K12 -> 317293.81 | L13: =L9-L12 -> 337025.58 | M13: =M9-M12 -> 355411.62
A14: Gross margin % | B14: 0.46905164 | C14: ='A1 Income Statement'!C13 -> 0.48158686 | D14: ='A1 Income Statement'!D13 -> 0.49270579 | E14: ='A1 Income Statement'!E13 -> 0.50056207 | F14: ='A1 Income Statement'!F13 -> 0.475 | G14: =G13/G9 -> 0.48696267 | H14: =H13/H9 -> 0.4924454 | I14: =I13/I9 -> 0.49761053 | J14: =J13/J9 -> 0.50272954 | K14: =K13/K9 -> 0.50756189 | L14: =L13/L9 -> 0.51202401 | M14: =M13/M9 -> 0.51585006
A15: Product gross margin % | B15: 0.3677065 | C15: ='A1 Income Statement'!C14 -> 0.40675031 | D15: ='A1 Income Statement'!D14 -> 0.38685667 | E15: ='A1 Income Statement'!E14 -> 0.4006838 | F15: ='A1 Income Statement'!F14 -> 0.36364189 | G15: =1-G10/G7 -> 0.39101708 | H15: =1-H10/H7 -> 0.394 | I15: =1-I10/I7 -> 0.396 | J15: =1-J10/J7 -> 0.398 | K15: =1-K10/K7 -> 0.4 | L15: =1-L10/L7 -> 0.402 | M15: =1-M10/M7 -> 0.404
A16: Services gross margin % | B16: 0.75408124 | C16: ='A1 Income Statement'!C15 -> 0.76520175 | D16: ='A1 Income Statement'!D15 -> 0.76678719 | E16: ='A1 Income Statement'!E15 -> 0.75620547 | F16: ='A1 Income Statement'!F15 -> 0.755 | G16: =1-G11/G8 -> 0.7607159 | H16: =1-H11/H8 -> 0.761 | I16: =1-I11/I8 -> 0.762 | J16: =1-J11/J8 -> 0.763 | K16: =1-K11/K8 -> 0.764 | L16: =1-L11/L8 -> 0.765 | M16: =1-M11/M8 -> 0.765
A18: Operating expenses
A19: Research and development | B19: 34550 | C19: ='A1 Income Statement'!C18 -> 10887 | D19: ='A1 Income Statement'!D18 -> 11419 | E19: ='A1 Income Statement'!E18 -> 11729 | F19: ='A1 Income Statement'!F18 -> 11836.605 | G19: =SUM(C19:F19) -> 45871.605 | H19: =H9*'D IS Assumptions'!F12 -> 49674.023 | I19: =I9*'D IS Assumptions'!F13 -> 52720.121 | J19: =J9*'D IS Assumptions'!F14 -> 55520.662 | K19: =K9*'D IS Assumptions'!F15 -> 58137.393 | L19: =L9*'D IS Assumptions'!F16 -> 60556.444 | M19: =M9*'D IS Assumptions'!F17 -> 62697.4
A20: Selling, general and administrative | B20: 27601 | C20: ='A1 Income Statement'!C19 -> 7492 | D20: ='A1 Income Statement'!D19 -> 7477 | E20: ='A1 Income Statement'!E19 -> 7346 | F20: ='A1 Income Statement'!F19 -> 7413.3945 | G20: =SUM(C20:F20) -> 29728.394 | H20: =H9*'D IS Assumptions'!G12 -> 32081.14 | I20: =I9*'D IS Assumptions'!G13 -> 33851.867 | J20: =J9*'D IS Assumptions'!G14 -> 35438.72 | K20: =K9*'D IS Assumptions'!G15 -> 36882.862 | L20: =L9*'D IS Assumptions'!G16 -> 38176.889 | M20: =M9*'D IS Assumptions'!G17 -> 39271.998
A21: Total operating expenses | B21: 62151 | C21: ='A1 Income Statement'!C20 -> 18379 | D21: ='A1 Income Statement'!D20 -> 18896 | E21: ='A1 Income Statement'!E20 -> 19075 | F21: ='A1 Income Statement'!F20 -> 19250 | G21: =SUM(C21:F21) -> 75600 | H21: =H19+H20 -> 81755.163 | I21: =I19+I20 -> 86571.988 | J21: =J19+J20 -> 90959.382 | K21: =K19+K20 -> 95020.255 | L21: =L19+L20 -> 98733.333 | M21: =M19+M20 -> 101969.4
A22: Operating income | B22: 133050 | C22: ='A1 Income Statement'!C21 -> 50852 | D22: ='A1 Income Statement'!D21 -> 35885 | E22: ='A1 Income Statement'!E21 -> 35695 | F22: ='A1 Income Statement'!F21 -> 34502.91 | G22: =SUM(C22:F22) -> 156934.91 | H22: =H13-H21 -> 173054.67 | I22: =I13-I21 -> 189576.3 | J22: =J13-J21 -> 205975.48 | K22: =K13-K21 -> 222273.56 | L22: =L13-L21 -> 238292.25 | M22: =M13-M21 -> 253442.22
A23: Operating margin % | B23: 0.319708 | C23: ='A1 Income Statement'!C22 -> 0.35373828 | D23: ='A1 Income Statement'!D22 -> 0.32275327 | E23: ='A1 Income Statement'!E22 -> 0.32622901 | F23: ='A1 Income Statement'!F22 -> 0.30489293 | G23: =G22/G9 -> 0.32864503 | H23: =H22/H9 -> 0.3344454 | I23: =I22/I9 -> 0.34161053 | J23: =J22/J9 -> 0.34872954 | K23: =K22/K9 -> 0.35556189 | L23: =L22/L9 -> 0.36202401 | M23: =M22/M9 -> 0.36785006
A25: Earnings and EPS
A26: Other income/(expense), net | B26: -321 | C26: ='A1 Income Statement'!C25 -> 150 | D26: ='A1 Income Statement'!D25 -> -52 | E26: ='A1 Income Statement'!E25 -> 572 | F26: ='A1 Income Statement'!F25 -> 350 | G26: =SUM(C26:F26) -> 1020 | H26: =H9*'D IS Assumptions'!H12 -> 1034.8755 | I26: =I9*'D IS Assumptions'!H13 -> 1109.8973 | J26: =J9*'D IS Assumptions'!H14 -> 1181.2907 | K26: =K9*'D IS Assumptions'!H15 -> 1250.2665 | L26: =L9*'D IS Assumptions'!H16 -> 1316.4444 | M26: =M9*'D IS Assumptions'!H17 -> 1377.9648
A27: Income before provision for income taxes | B27: 132729 | C27: ='A1 Income Statement'!C26 -> 51002 | D27: ='A1 Income Statement'!D26 -> 35833 | E27: ='A1 Income Statement'!E26 -> 36267 | F27: ='A1 Income Statement'!F26 -> 34852.91 | G27: =SUM(C27:F27) -> 157954.91 | H27: =H22+H26 -> 174089.55 | I27: =I22+I26 -> 190686.2 | J27: =J22+J26 -> 207156.77 | K27: =K22+K26 -> 223523.83 | L27: =L22+L26 -> 239608.69 | M27: =M22+M26 -> 254820.19
A28: Effective tax rate | B28: 0.15610002 | C28: ='A1 Income Statement'!C27 -> 0.174601 | D28: ='A1 Income Statement'!D27 -> 0.17455976 | E28: ='A1 Income Statement'!E27 -> 0.17861968 | F28: ='A1 Income Statement'!F27 -> 0.165 | G28: =G29/G27 -> 0.17339588 | H28: ='D IS Assumptions'!I12 -> 0.165 | I28: ='D IS Assumptions'!I13 -> 0.165 | J28: ='D IS Assumptions'!I14 -> 0.165 | K28: ='D IS Assumptions'!I15 -> 0.165 | L28: ='D IS Assumptions'!I16 -> 0.165 | M28: ='D IS Assumptions'!I17 -> 0.165
A29: Provision for income taxes | B29: 20719 | C29: ='A1 Income Statement'!C28 -> 8905 | D29: ='A1 Income Statement'!D28 -> 6255 | E29: ='A1 Income Statement'!E28 -> 6478 | F29: ='A1 Income Statement'!F28 -> 5750.7301 | G29: =SUM(C29:F29) -> 27388.73 | H29: =H27*H28 -> 28724.775 | I29: =I27*I28 -> 31463.223 | J29: =J27*J28 -> 34180.867 | K29: =K27*K28 -> 36881.431 | L29: =L27*L28 -> 39535.434 | M29: =M27*M28 -> 42045.331
A30: Net income | B30: 112010 | C30: ='A1 Income Statement'!C29 -> 42097 | D30: ='A1 Income Statement'!D29 -> 29578 | E30: ='A1 Income Statement'!E29 -> 29789 | F30: ='A1 Income Statement'!F29 -> 29102.179 | G30: =SUM(C30:F30) -> 130566.18 | H30: =H27-H29 -> 145364.77 | I30: =I27-I29 -> 159222.98 | J30: =J27-J29 -> 172975.9 | K30: =K27-K29 -> 186642.39 | L30: =L27-L29 -> 200073.26 | M30: =M27-M29 -> 212774.86
A31: Net margin % | B31: 0.26915064 | C31: =C30/C9 -> 0.29283647 | D31: =D30/D9 -> 0.26602749 | E31: =E30/E9 -> 0.27225203 | F31: =F30/F9 -> 0.25716813 | G31: =G30/G9 -> 0.27342499 | H31: =H30/H9 -> 0.28093191 | I31: =I30/I9 -> 0.2869148 | J31: =J30/J9 -> 0.29285917 | ... M31: =M30/M9 -> 0.3088248
A32: Diluted weighted-average shares (millions) | B32: 15004.7 | C32: ='A1 Income Statement'!C30 -> 14810.36 | D32: ='A1 Income Statement'!D30 -> 14725.87 | E32: ='A1 Income Statement'!E30 -> 14714.68 | F32: ='A1 Income Statement'!F30 -> 14650 | G32: =AVERAGE(C32:F32) -> 14725.228 | H32: =G32*(1+'D IS Assumptions'!J12) -> 14430.723 | I32: =H32*(1+'D IS Assumptions'!J13) -> 14142.108 | J32: =I32*(1+'D IS Assumptions'!J14) -> 13859.266 | K32: =J32*(1+'D IS Assumptions'!J15) -> 13582.081 | L32: =K32*(1+'D IS Assumptions'!J16) -> 13310.439 | M32: =L32*(1+'D IS Assumptions'!J17) -> 13044.231
A33: Diluted EPS | B33: 7.46 | C33: ='A1 Income Statement'!C31 -> 2.84 | D33: ='A1 Income Statement'!D31 -> 2.01 | E33: ='A1 Income Statement'!E31 -> 2.02 | F33: ='A1 Income Statement'!F31 -> 1.9864969 | G33: =G30/G32 -> 8.8668361 | H33: =H30/H32 -> 10.073284 | I33: =I30/I32 -> 11.258786 | J33: =J30/J32 -> 12.480885 | K33: =K30/K32 -> 13.741811 | L33: =L30/L32 -> 15.031304 | M33: =M30/M32 -> 16.311798
A34: Net sales growth | G34: =G9/B9-1 -> 0.14744298 | H34: =H9/G9-1 -> 0.08359155 | I34: =I9/H9-1 -> 0.072493544 | J34: =J9/I9-1 -> 0.064324327 | K34: =K9/J9-1 -> 0.058390234 | L34: =L9/K9-1 -> 0.052931059 | M34: =M9/L9-1 -> 0.046732233
A35: Diluted EPS growth | G35: =G33/B33-1 -> 0.18858393 | H35: =H33/G33-1 -> 0.13606296 | I35: =I33/H33-1 -> 0.11768774 | J35: =J33/I33-1 -> 0.10854619 | K35: =K33/J33-1 -> 0.10102864 | L35: =L33/K33-1 -> 0.093837154 | M35: =M33/L33-1 -> 0.085188513
A37: Forecast checks
A38: Gross margin check | B38: =B13-(B9-B12) -> 0 | C38: =C13-(C9-C12) -> 0 | D38: =D13-(D9-D12) -> 0 | E38: =E13-(E9-E12) -> 0 | F38: =F13-(F9-F12) -> 0 | G38: =G13-(G9-G12) -> 0 | H38: =H13-(H9-H12) -> 0 | I38: =I13-(I9-I12) -> 0 | ... M38: =M13-(M9-M12) -> 0
A39: Operating income check | B39: =B22-(B13-B21) -> 0 | C39: =C22-(C13-C21) -> 0 | D39: =D22-(D13-D21) -> 0 | E39: =E22-(E13-E21) -> 0 | F39: =F22-(F13-F21) -> 0 | G39: =G22-(G13-G21) -> 0 | H39: =H22-(H13-H21) -> 0 | I39: =I22-(I13-I21) -> 0 | ... M39: =M22-(M13-M21) -> 0
A40: Net income check | B40: =B30-(B27-B29) -> 0 | C40: =C30-(C27-C29) -> 0 | D40: =D30-(D27-D29) -> 0 | E40: =E30-(E27-E29) -> 0 | F40: =F30-(F27-F29) -> 0 | G40: =G30-(G27-G29) -> 0 | H40: =H30-(H27-H29) -> 0 | I40: =I30-(I27-I29) -> 0 | ... M40: =M30-(M27-M29) -> 0
A41: FY2026 annual revenue bridge check | G41: =G9-SUM(C9:F9) -> 0

Sheet D IS Assumptions
A2: Income Statement Forecast Assumptions
A3: Historical rates are shown for calibration. Detailed revenue-growth inputs are yellow on C1 Revenue Build; other yellow cells below remain editable base-case assumptions.
A5: Fiscal year | B5: Products growth (derived) | C5: Services growth (derived) | D5: Product gross margin | E5: Services gross margin | F5: R&D / sales | G5: SG&A / sales | H5: Other income / sales | I5: Effective tax rate | J5: Diluted share change | K5: Basis | L5: Forecast rationale | M5: Primary source
A6: FY2021 Actual | D6: 0.35349303 | E6: 0.69725977 | F6: 0.059904269 | G6: 0.060065552 | H6: 0.00070527067 | I6: 0.13302261 | K6: Historical actual | L6: Historical calibration | M6: Supplied AAPL financials; Apple annual filings
A7: FY2022 Actual | B7: 0.063239764 | C7: 0.14181951 | D7: 0.3628348 | E7: 0.71745447 | F7: 0.066571484 | G7: 0.063637378 | H7: -0.00084701061 | I7: 0.16204462 | J7: -0.031965761 | K7: Historical actual | L7: Historical calibration | M7: Supplied AAPL financials; Apple annual filings
A8: FY2023 Actual | B8: -0.057286709 | C8: 0.090504166 | D8: 0.36500663 | E8: 0.70827465 | F8: 0.078048971 | G8: 0.065048202 | H8: -0.0014740989 | I8: 0.14719174 | J8: -0.031439156 | K8: Historical actual | L8: Historical calibration | M8: Supplied AAPL financials; Apple annual filings
A9: FY2024 Actual | B9: -0.010798933 | C9: 0.12874413 | D9: 0.37180618 | E9: 0.73880356 | F9: 0.080222998 | G9: 0.066738272 | H9: 0.00068791796 | I9: 0.24091185 | J9: -0.025577785 | K9: Historical actual | L9: Historical calibration | M9: Supplied AAPL financials; Apple annual filings
A10: FY2025 Actual | B10: 0.04116107 | C10: 0.13506431 | D10: 0.3677065 | E10: 0.75408124 | F10: 0.083020754 | G10: 0.066322889 | H10: -0.00077133609 | I10: 0.15610002 | J10: -0.026181035 | K10: Historical actual | L10: Historical calibration | M10: Supplied AAPL financials; Apple annual filings
A11: FY2026 Forecast | B11: ='C2 Annual IS Forecast'!G7/'C2 Annual IS Forecast'!B7-1 -> 0.15175754 | C11: ='C2 Annual IS Forecast'!G8/'C2 Annual IS Forecast'!B8-1 -> 0.13530845 | D11: ='C2 Annual IS Forecast'!G15 -> 0.39101708 | E11: ='C2 Annual IS Forecast'!G16 -> 0.7607159 | F11: ='C2 Annual IS Forecast'!G19/'C2 Annual IS Forecast'!G9 -> 0.096061961 | G11: ='C2 Annual IS Forecast'!G20/'C2 Annual IS Forecast'!G9 -> 0.062255677 | H11: ='C2 Annual IS Forecast'!G26/'C2 Annual IS Forecast'!G9 -> 0.0021360316 | I11: ='C2 Annual IS Forecast'!G28 -> 0.17339588 | J11: ='C2 Annual IS Forecast'!G32/'C2 Annual IS Forecast'!B32-1 -> -0.018625664 | K11: Q1-Q3 actual + Q4 forecast | L11: Uses the group Q4 model and current-year actual results. | M11: Apple FY2026 Q3 Form 10-Q and group Q4 forecast
A12: FY2027 Forecast | B12: ='C1 Revenue Build'!C23/'C1 Revenue Build'!B23-1 -> 0.070831043 | C12: ='C1 Revenue Build'!C22/'C1 Revenue Build'!B22-1 -> 0.12 | D12: 0.394 | E12: 0.761 | F12: 0.096 | G12: 0.062 | H12: 0.002 | I12: 0.165 | J12: -0.02 | K12: Base case | L12: Bottom-up revenue build: iPhone 8.0%, Mac 6.0%, iPad 3.0%, Wearables 5.0%, Services 12.0%. Aggregate Products growth is formula-derived. | M12: C1 Revenue Build; Apple FY2026 Q3 results; normalized base case
A13: FY2028 Forecast | B13: ='C1 Revenue Build'!D23/'C1 Revenue Build'!C23-1 -> 0.058744616 | C13: ='C1 Revenue Build'!D22/'C1 Revenue Build'!C22-1 -> 0.11 | D13: 0.396 | E13: 0.762 | F13: 0.095 | G13: 0.061 | H13: 0.002 | I13: 0.165 | J13: -0.02 | K13: Base case | L13: Bottom-up revenue build: iPhone 6.5%, Mac 5.0%, iPad 3.0%, Wearables 4.5%, Services 11.0%. Aggregate Products growth is formula-derived. | M13: C1 Revenue Build; Apple FY2026 Q3 results; normalized base case
A14: FY2029 Forecast | B14: ='C1 Revenue Build'!E23/'C1 Revenue Build'!D23-1 -> 0.050613402 | C14: ='C1 Revenue Build'!E22/'C1 Revenue Build'!D22-1 -> 0.1 | D14: 0.398 | E14: 0.763 | F14: 0.094 | G14: 0.06 | H14: 0.002 | I14: 0.165 | J14: -0.02 | K14: Base case | L14: Bottom-up revenue build: iPhone 5.5%, Mac 4.5%, iPad 3.0%, Wearables 4.0%, Services 10.0%. Aggregate Products growth is formula-derived. | M14: C1 Revenue Build; Apple FY2026 Q3 results; normalized base case
A15: FY2030 Forecast | B15: ='C1 Revenue Build'!F23/'C1 Revenue Build'!E23-1 -> 0.045670863 | C15: ='C1 Revenue Build'!F22/'C1 Revenue Build'!E22-1 -> 0.09 | D15: 0.4 | E15: 0.764 | F15: 0.093 | G15: 0.059 | H15: 0.002 | I15: 0.165 | J15: -0.02 | K15: Base case | L15: Bottom-up revenue build: iPhone 5.0%, Mac 4.0%, iPad 2.5%, Wearables 3.5%, Services 9.0%. Aggregate Products growth is formula-derived. | M15: C1 Revenue Build; Apple FY2026 Q3 results; normalized base case
A16: FY2031 Forecast | B16: ='C1 Revenue Build'!G23/'C1 Revenue Build'!F23-1 -> 0.041577106 | C16: ='C1 Revenue Build'!G22/'C1 Revenue Build'!F22-1 -> 0.08 | D16: 0.402 | E16: 0.765 | F16: 0.092 | G16: 0.058 | H16: 0.002 | I16: 0.165 | J16: -0.02 | K16: Base case | L16: Bottom-up revenue build: iPhone 4.5%, Mac 3.5%, iPad 2.5%, Wearables 3.5%, Services 8.0%. Aggregate Products growth is formula-derived. | M16: C1 Revenue Build; Apple FY2026 Q3 results; normalized base case
A17: FY2032 Forecast | B17: ='C1 Revenue Build'!H23/'C1 Revenue Build'!G23-1 -> 0.036612644 | C17: ='C1 Revenue Build'!H22/'C1 Revenue Build'!G22-1 -> 0.07 | D17: 0.404 | E17: 0.765 | F17: 0.091 | G17: 0.057 | H17: 0.002 | I17: 0.165 | J17: -0.02 | K17: Base case | L17: Bottom-up revenue build: iPhone 4.0%, Mac 3.0%, iPad 2.0%, Wearables 3.0%, Services 7.0%. Aggregate Products growth is formula-derived. | M17: C1 Revenue Build; Apple FY2026 Q3 results; normalized base case
A19: Source references | K19: Driver rationale
A20: Apple FY2026 Q3 results | D20: https://www.apple.com/newsroom/2026/07/apple-reports-third-quarter-results/ | K20: Driver | L20: Forecast approach | M20: Evidence and source
A21: Apple FY2026 Q3 Form 10-Q | D21: https://www.sec.gov/Archives/edgar/data/320193/000032019326000020/aapl-20260627.htm | K21: Products growth | L21: Aggregate Products growth is derived from separate iPhone, Mac, iPad and Wearables assumptions on C1 Revenue Build. | M21: Apple category revenue disclosures; team base-case assumptions
A22: Apple FY2025 consolidated financial statements | D22: https://www.apple.com/newsroom/pdfs/fy2025-q4/FY25_Q4_Consolidated_Financial_Statements.pdf | K22: Services growth | L22: Services growth remains a separate category assumption on C1 Revenue Build and declines from 12.0% to 7.0%. | M22: Apple Services history; team base-case assumptions
K23: Gross margins | L23: Increase Product margin gradually from 39.4% to 40.4%; keep Services margin near 76%. The rising Services mix lifts total gross margin without a step change. | M23: Segment margin history and FY2026 quarterly results
K24: Operating expenses | L24: Keep R&D above 9% of sales to support product and AI investment; allow SG&A to decline gradually as a percentage of sales. | M24: Historical R&D and SG&A ratios
K25: Other income and tax | L25: Hold other income near 0.2% of sales and use a 16.5% tax rate. The FY2024 tax rate is not used because it included an unusual tax item. | M25: FY2025 filing and current-year guidance
K26: Diluted shares | L26: Reduce diluted shares by 2.0% per year. This is conservative relative to recent declines of roughly 2.6%-3.2% and remains consistent with continued repurchases. | M26: FY2021-FY2026 share-count history

Sheet E IS Outputs for BS
A2: Income Statement Outputs for Balance Sheet Forecast
A3: Use these linked annual values for FY2027-FY2032 balance-sheet drivers; FY2026 year-end balances equal the Q4 ending balance and should not be summed across quarters
A5: Metric | B5: FY2026 Forecast | C5: FY2027 Forecast | D5: FY2028 Forecast | E5: FY2029 Forecast | F5: FY2030 Forecast | G5: FY2031 Forecast | H5: FY2032 Forecast | I5: Suggested balance-sheet use
A6: Net sales | B6: ='C2 Annual IS Forecast'!G9 -> 477521.02 | C6: ='C2 Annual IS Forecast'!H9 -> 517437.74 | D6: ='C2 Annual IS Forecast'!I9 -> 554948.64 | E6: ='C2 Annual IS Forecast'!J9 -> 590645.34 | F6: ='C2 Annual IS Forecast'!K9 -> 625133.26 | G6: ='C2 Annual IS Forecast'!L9 -> 658222.22 | H6: ='C2 Annual IS Forecast'!M9 -> 688982.42 | I6: A/R and deferred revenue turnover
A7: Cost of sales | B7: ='C2 Annual IS Forecast'!G12 -> 244986.11 | C7: ='C2 Annual IS Forecast'!H12 -> 262627.91 | D7: ='C2 Annual IS Forecast'!I12 -> 278800.35 | E7: ='C2 Annual IS Forecast'!J12 -> 293710.48 | F7: ='C2 Annual IS Forecast'!K12 -> 307839.44 | G7: ='C2 Annual IS Forecast'!L12 -> 321196.64 | H7: ='C2 Annual IS Forecast'!M12 -> 333570.79 | I7: Inventory, vendor receivables and A/P turnover
A8: Gross margin | B8: ='C2 Annual IS Forecast'!G13 -> 232534.91 | C8: ='C2 Annual IS Forecast'!H13 -> 254809.84 | D8: ='C2 Annual IS Forecast'!I13 -> 276148.29 | E8: ='C2 Annual IS Forecast'!J13 -> 296934.86 | F8: ='C2 Annual IS Forecast'!K13 -> 317293.81 | G8: ='C2 Annual IS Forecast'!L13 -> 337025.58 | H8: ='C2 Annual IS Forecast'!M13 -> 355411.62 | I8: Profitability and retained operating capacity
A9: Operating income | B9: ='C2 Annual IS Forecast'!G22 -> 156934.91 | C9: ='C2 Annual IS Forecast'!H22 -> 173054.67 | D9: ='C2 Annual IS Forecast'!I22 -> 189576.3 | E9: ='C2 Annual IS Forecast'!J22 -> 205975.48 | F9: ='C2 Annual IS Forecast'!K22 -> 222273.56 | G9: ='C2 Annual IS Forecast'!L22 -> 238292.25 | H9: ='C2 Annual IS Forecast'!M22 -> 253442.22 | I9: Operating profitability and valuation
A10: Net income | B10: ='C2 Annual IS Forecast'!G30 -> 130566.18 | C10: ='C2 Annual IS Forecast'!H30 -> 145364.77 | D10: ='C2 Annual IS Forecast'!I30 -> 159222.98 | E10: ='C2 Annual IS Forecast'!J30 -> 172975.9 | F10: ='C2 Annual IS Forecast'!K30 -> 186642.39 | G10: ='C2 Annual IS Forecast'!L30 -> 200073.26 | H10: ='C2 Annual IS Forecast'!M30 -> 212774.86 | I10: Retained earnings roll-forward
A11: Diluted weighted-average shares | B11: ='C2 Annual IS Forecast'!G32 -> 14725.228 | C11: ='C2 Annual IS Forecast'!H32 -> 14430.723 | D11: ='C2 Annual IS Forecast'!I32 -> 14142.108 | E11: ='C2 Annual IS Forecast'!J32 -> 13859.266 | F11: ='C2 Annual IS Forecast'!K32 -> 13582.081 | G11: ='C2 Annual IS Forecast'!L32 -> 13310.439 | H11: ='C2 Annual IS Forecast'!M32 -> 13044.231 | I11: Share-count and repurchase consistency
A12: Diluted EPS | B12: ='C2 Annual IS Forecast'!G33 -> 8.8668361 | C12: ='C2 Annual IS Forecast'!H33 -> 10.073284 | D12: ='C2 Annual IS Forecast'!I33 -> 11.258786 | E12: ='C2 Annual IS Forecast'!J33 -> 12.480885 | F12: ='C2 Annual IS Forecast'!K33 -> 13.741811 | G12: ='C2 Annual IS Forecast'!L33 -> 15.031304 | H12: ='C2 Annual IS Forecast'!M33 -> 16.311798 | I12: Valuation and reasonableness check
A13: Net sales growth | B13: ='C2 Annual IS Forecast'!G34 -> 0.14744298 | C13: ='C2 Annual IS Forecast'!H34 -> 0.08359155 | D13: ='C2 Annual IS Forecast'!I34 -> 0.072493544 | E13: ='C2 Annual IS Forecast'!J34 -> 0.064324327 | F13: ='C2 Annual IS Forecast'!K34 -> 0.058390234 | G13: ='C2 Annual IS Forecast'!L34 -> 0.052931059 | H13: ='C2 Annual IS Forecast'!M34 -> 0.046732233 | I13: Growth calibration for operating balances
A14: Cost of sales growth | B14: ='C2 Annual IS Forecast'!G12/'C2 Annual IS Forecast'!B12-1 -> 0.10873511 | C14: ='C2 Annual IS Forecast'!H12/'C2 Annual IS Forecast'!G12-1 -> 0.072011414 | D14: ='C2 Annual IS Forecast'!I12/'C2 Annual IS Forecast'!H12-1 -> 0.061579301 | E14: ='C2 Annual IS Forecast'!J12/'C2 Annual IS Forecast'!I12-1 -> 0.053479581 | F14: ='C2 Annual IS Forecast'!K12/'C2 Annual IS Forecast'!J12-1 -> 0.048105081 | G14: ='C2 Annual IS Forecast'!L12/'C2 Annual IS Forecast'!K12-1 -> 0.043390147 | H14: ='C2 Annual IS Forecast'!M12/'C2 Annual IS Forecast'!L12-1 -> 0.038525167 | I14: Calculated year-over-year change
A15: Net margin | B15: ='C2 Annual IS Forecast'!G31 -> 0.27342499 | C15: ='C2 Annual IS Forecast'!H31 -> 0.28093191 | D15: ='C2 Annual IS Forecast'!I31 -> 0.2869148 | E15: ='C2 Annual IS Forecast'!J31 -> 0.29285917 | F15: ='C2 Annual IS Forecast'!K31 -> 0.29856417 | G15: ='C2 Annual IS Forecast'!L31 -> 0.30396005 | H15: ='C2 Annual IS Forecast'!M31 -> 0.3088248 | I15: Profitability and retained earnings review
A17: Shared follow-up | I17: Agree dividends and share repurchases before completing retained earnings and cash.
A18: Model handoff | I18: Link to the cells above rather than copying values so later assumption changes flow through.
A19: FY2026 balance-sheet base | I19: Use the existing FY2026 Q4 forecast column in B Balance Sheet as the FY2026 year-end starting point.

Sheet F BS Assumptions
A2: Annual Balance Sheet Assumptions
A3: USD millions; FY2026 base uses the forecast 2026 fiscal year-end balance and FY2026 annual income.
A5: Driver | B5: FY2026 Base | C5: FY2027 Forecast | D5: FY2028 Forecast | E5: FY2029 Forecast | F5: FY2030 Forecast | G5: FY2031 Forecast | H5: FY2032 Forecast
A6: Net sales | B6: ='E IS Outputs for BS'!B6 -> 477521.02 | C6: ='E IS Outputs for BS'!C6 -> 517437.74 | D6: ='E IS Outputs for BS'!D6 -> 554948.64 | E6: ='E IS Outputs for BS'!E6 -> 590645.34 | F6: ='E IS Outputs for BS'!F6 -> 625133.26 | G6: ='E IS Outputs for BS'!G6 -> 658222.22 | H6: ='E IS Outputs for BS'!H6 -> 688982.42
A7: Cost of sales | B7: ='E IS Outputs for BS'!B7 -> 244986.11 | C7: ='E IS Outputs for BS'!C7 -> 262627.91 | D7: ='E IS Outputs for BS'!D7 -> 278800.35 | E7: ='E IS Outputs for BS'!E7 -> 293710.48 | F7: ='E IS Outputs for BS'!F7 -> 307839.44 | G7: ='E IS Outputs for BS'!G7 -> 321196.64 | H7: ='E IS Outputs for BS'!H7 -> 333570.79
A8: Net income | B8: ='E IS Outputs for BS'!B10 -> 130566.18 | C8: ='E IS Outputs for BS'!C10 -> 145364.77 | D8: ='E IS Outputs for BS'!D10 -> 159222.98 | E8: ='E IS Outputs for BS'!E10 -> 172975.9 | F8: ='E IS Outputs for BS'!F10 -> 186642.39 | G8: ='E IS Outputs for BS'!G10 -> 200073.26 | H8: ='E IS Outputs for BS'!H10 -> 212774.86
A10: Year-end ratios and turnover
A11: Cash / annual sales | B11: ='B Balance Sheet'!D7/B6 -> 0.061209832 | C11: =$B11 -> 0.061209832 | D11: =$B11 -> 0.061209832 | E11: =$B11 -> 0.061209832 | F11: =$B11 -> 0.061209832 | G11: =$B11 -> 0.061209832 | H11: =$B11 -> 0.061209832
A12: Current marketable securities / sales | B12: ='B Balance Sheet'!D8/B6 -> 0.047861767 | C12: =$B12 -> 0.047861767 | D12: =$B12 -> 0.047861767 | E12: =$B12 -> 0.047861767 | F12: =$B12 -> 0.047861767 | G12: =$B12 -> 0.047861767 | H12: =$B12 -> 0.047861767
A13: A/R turnover: annual sales / year-end A/R | B13: =B6/'B Balance Sheet'!D9 -> 10.870059 | C13: =$B13 -> 10.870059 | D13: =$B13 -> 10.870059 | E13: =$B13 -> 10.870059 | F13: =$B13 -> 10.870059 | G13: =$B13 -> 10.870059 | H13: =$B13 -> 10.870059
A14: Vendor receivables turnover: COGS / year-end balance | B14: =B7/'B Balance Sheet'!D10 -> 6.7265956 | C14: =$B14 -> 6.7265956 | D14: =$B14 -> 6.7265956 | E14: =$B14 -> 6.7265956 | F14: =$B14 -> 6.7265956 | G14: =$B14 -> 6.7265956 | H14: =$B14 -> 6.7265956
A15: Inventory turnover: COGS / year-end inventory | B15: =B7/'B Balance Sheet'!D11 -> 20.315628 | C15: =$B15 -> 20.315628 | D15: =$B15 -> 20.315628 | E15: =$B15 -> 20.315628 | F15: =$B15 -> 20.315628 | G15: =$B15 -> 20.315628 | H15: =$B15 -> 20.315628
A16: Other current assets / sales | B16: ='B Balance Sheet'!D12/B6 -> 0.03648007 | C16: =$B16 -> 0.03648007 | D16: =$B16 -> 0.03648007 | E16: =$B16 -> 0.03648007 | F16: =$B16 -> 0.03648007 | G16: =$B16 -> 0.03648007 | H16: =$B16 -> 0.03648007
A17: Non-current marketable securities / sales | B17: ='B Balance Sheet'!D16/B6 -> 0.1761556 | C17: =$B17 -> 0.1761556 | D17: =$B17 -> 0.1761556 | E17: =$B17 -> 0.1761556 | F17: =$B17 -> 0.1761556 | G17: =$B17 -> 0.1761556 | H17: =$B17 -> 0.1761556
A18: PP&E / sales | B18: ='B Balance Sheet'!D17/B6 -> 0.10770416 | C18: =$B18 -> 0.10770416 | D18: =$B18 -> 0.10770416 | E18: =$B18 -> 0.10770416 | F18: =$B18 -> 0.10770416 | G18: =$B18 -> 0.10770416 | H18: =$B18 -> 0.10770416
A19: Intangible assets / sales | B19: ='B Balance Sheet'!D18/B6 -> 0.042599172 | C19: =$B19 -> 0.042599172 | D19: =$B19 -> 0.042599172 | E19: =$B19 -> 0.042599172 | F19: =$B19 -> 0.042599172 | G19: =$B19 -> 0.042599172 | H19: =$B19 -> 0.042599172
A20: Other non-current assets / sales | B20: ='B Balance Sheet'!D19/B6 -> 0.16241589 | C20: =$B20 -> 0.16241589 | D20: =$B20 -> 0.16241589 | E20: =$B20 -> 0.16241589 | F20: =$B20 -> 0.16241589 | G20: =$B20 -> 0.16241589 | H20: =$B20 -> 0.16241589
A21: A/P turnover: COGS / year-end A/P | B21: =B7/'B Balance Sheet'!D24 -> 3.1947959 | C21: =$B21 -> 3.1947959 | D21: =$B21 -> 3.1947959 | E21: =$B21 -> 3.1947959 | F21: =$B21 -> 3.1947959 | G21: =$B21 -> 3.1947959 | H21: =$B21 -> 3.1947959
A22: Deferred revenue turnover: sales / year-end balance | B22: =B6/'B Balance Sheet'!D26 -> 47.750229 | C22: =$B22 -> 47.750229 | D22: =$B22 -> 47.750229 | E22: =$B22 -> 47.750229 | F22: =$B22 -> 47.750229 | G22: =$B22 -> 47.750229 | H22: =$B22 -> 47.750229
A23: Other current liabilities / sales | B23: ='B Balance Sheet'!D25/B6 -> 0.1303796 | C23: =$B23 -> 0.1303796 | D23: =$B23 -> 0.1303796 | E23: =$B23 -> 0.1303796 | F23: =$B23 -> 0.1303796 | G23: =$B23 -> 0.1303796 | H23: =$B23 -> 0.1303796
A24: Other non-current liabilities / sales | B24: ='B Balance Sheet'!D32/B6 -> 0.11534571 | C24: =$B24 -> 0.11534571 | D24: =$B24 -> 0.11534571 | E24: =$B24 -> 0.11534571 | F24: =$B24 -> 0.11534571 | G24: =$B24 -> 0.11534571 | H24: =$B24 -> 0.11534571
A26: Capital allocation and financing
A27: Annual debt balance change | C27: -0.03 | D27: -0.03 | E27: -0.03 | F27: -0.03 | G27: -0.03 | H27: -0.03
A28: Annual dividend growth | C28: 0.03 | D28: 0.03 | E28: 0.03 | F28: 0.03 | G28: 0.03 | H28: 0.03
A29: Dividends declared, FY2026 base | B29: =11733+'A2 Q4 Drivers'!D22 -> 15731
A30: Share repurchases recognized, FY2026 base | B30: =62242+'A2 Q4 Drivers'!D23 -> 88191
A31: Diluted share change from A model | B31: ='A1 Income Statement'!F30 -> 14650 | C31: ='D IS Assumptions'!J12 -> -0.02 | D31: ='D IS Assumptions'!J13 -> -0.02 | E31: ='D IS Assumptions'!J14 -> -0.02 | F31: ='D IS Assumptions'!J15 -> -0.02 | G31: ='D IS Assumptions'!J16 -> -0.02 | H31: ='D IS Assumptions'!J17 -> -0.02
A34: Why these assumptions are used
A35: Working capital | K35: Use FY2026 annual flows divided by the forecast year-end 2026 balance. Hold the resulting turnover ratios for 2027-2032; this avoids using quarterly flows against annual balances.
A36: Operating assets and liabilities | K36: Scale cash, investments, PP&E, intangibles and other balances with annual sales; use COGS for inventory and vendor payables/receivables.
A37: Financing | K37: Amortize commercial paper and term debt balances by 3% annually; no new issuance is assumed. This lowers debt/equity over time.
A38: Equity and cash | K38: Keep APIC and AOCI flat after FY2026 for clean-surplus valuation. Set cash to the FY2026 cash/sales ratio; repurchases absorb residual distributable cash.
A39: Dividends | K39: FY2026 declared dividends = 11,733 for Q1-Q3 plus the Q4 estimate 3,998. Grow 3% per year thereafter.
A40: Share count | K40: Use A model diluted shares, falling 2% per year. The balance-sheet model reports the implied average buyback price as a consistency check.
A41: FY2026 buybacks | K41: FY2026 recognized repurchases = 62,242 for Q1-Q3 plus the Q4 estimate 25,949. Annual later-year buybacks are calculated, not assumed.
A42: Source | K42: Apple FY2026 Q3 Form 10-Q equity statement and the supplied integrated forecast. https://www.sec.gov/Archives/edgar/data/320193/000032019326000020/aapl-20260627.htm

Sheet G Annual BS Forecast
A2: FY2026-FY2032 Annual Balance Sheet
A3: USD millions; FY2026 is the group Q4 year-end forecast; later-year drivers are on F BS Assumptions.
A5: Balance sheet item | B5: FY2026 Base | C5: FY2027 Forecast | D5: FY2028 Forecast | E5: FY2029 Forecast | F5: FY2030 Forecast | G5: FY2031 Forecast | H5: FY2032 Forecast
A6: Current assets
A7: Cash and cash equivalents | B7: ='B Balance Sheet'!D7 -> 29228.981 | C7: ='F BS Assumptions'!C6*'F BS Assumptions'!C11 -> 31672.277 | D7: ='F BS Assumptions'!D6*'F BS Assumptions'!D11 -> 33968.313 | E7: ='F BS Assumptions'!E6*'F BS Assumptions'!E11 -> 36153.302 | F7: ='F BS Assumptions'!F6*'F BS Assumptions'!F11 -> 38264.301 | G7: ='F BS Assumptions'!G6*'F BS Assumptions'!G11 -> 40289.671 | H7: ='F BS Assumptions'!H6*'F BS Assumptions'!H11 -> 42172.498
A8: Current marketable securities | B8: ='B Balance Sheet'!D8 -> 22855 | C8: ='F BS Assumptions'!C6*'F BS Assumptions'!C12 -> 24765.485 | D8: ='F BS Assumptions'!D6*'F BS Assumptions'!D12 -> 26560.823 | E8: ='F BS Assumptions'!E6*'F BS Assumptions'!E12 -> 28269.33 | F8: ='F BS Assumptions'!F6*'F BS Assumptions'!F12 -> 29919.982 | G8: ='F BS Assumptions'!G6*'F BS Assumptions'!G12 -> 31503.679 | H8: ='F BS Assumptions'!H6*'F BS Assumptions'!H12 -> 32975.916
A9: Accounts receivable, net | B9: ='B Balance Sheet'!D9 -> 43929.94 | C9: ='F BS Assumptions'!C6/'F BS Assumptions'!C13 -> 47602.112 | D9: ='F BS Assumptions'!D6/'F BS Assumptions'!D13 -> 51052.957 | E9: ='F BS Assumptions'!E6/'F BS Assumptions'!E13 -> 54336.905 | F9: ='F BS Assumptions'!F6/'F BS Assumptions'!F13 -> 57509.649 | G9: ='F BS Assumptions'!G6/'F BS Assumptions'!G13 -> 60553.696 | H9: ='F BS Assumptions'!H6/'F BS Assumptions'!H13 -> 63383.505
A10: Vendor non-trade receivables | B10: ='B Balance Sheet'!D10 -> 36420.52 | C10: ='F BS Assumptions'!C7/'F BS Assumptions'!C14 -> 39043.213 | D10: ='F BS Assumptions'!D7/'F BS Assumptions'!D14 -> 41447.467 | E10: ='F BS Assumptions'!E7/'F BS Assumptions'!E14 -> 43664.06 | F10: ='F BS Assumptions'!F7/'F BS Assumptions'!F14 -> 45764.523 | G10: ='F BS Assumptions'!G7/'F BS Assumptions'!G14 -> 47750.253 | H10: ='F BS Assumptions'!H7/'F BS Assumptions'!H14 -> 49589.839
A11: Inventories | B11: ='B Balance Sheet'!D11 -> 12058.998 | C11: ='F BS Assumptions'!C7/'F BS Assumptions'!C15 -> 12927.383 | D11: ='F BS Assumptions'!D7/'F BS Assumptions'!D15 -> 13723.442 | E11: ='F BS Assumptions'!E7/'F BS Assumptions'!E15 -> 14457.366 | F11: ='F BS Assumptions'!F7/'F BS Assumptions'!F15 -> 15152.839 | G11: ='F BS Assumptions'!G7/'F BS Assumptions'!G15 -> 15810.323 | H11: ='F BS Assumptions'!H7/'F BS Assumptions'!H15 -> 16419.418
A12: Other current assets | B12: ='B Balance Sheet'!D12 -> 17420 | C12: ='F BS Assumptions'!C6*'F BS Assumptions'!C16 -> 18876.165 | D12: ='F BS Assumptions'!D6*'F BS Assumptions'!D16 -> 20244.565 | E12: ='F BS Assumptions'!E6*'F BS Assumptions'!E16 -> 21546.783 | F12: ='F BS Assumptions'!F6*'F BS Assumptions'!F16 -> 22804.905 | G12: ='F BS Assumptions'!G6*'F BS Assumptions'!G16 -> 24011.992 | H12: ='F BS Assumptions'!H6*'F BS Assumptions'!H16 -> 25134.126
A13: Total current assets | B13: ='B Balance Sheet'!D13 -> 161913.44 | C13: =SUM(C7:C12) -> 174886.63 | D13: =SUM(D7:D12) -> 186997.57 | E13: =SUM(E7:E12) -> 198427.75 | F13: =SUM(F7:F12) -> 209416.2 | G13: =SUM(G7:G12) -> 219919.61 | H13: =SUM(H7:H12) -> 229675.3
A15: Non-current assets
A16: Non-current marketable securities | B16: ='B Balance Sheet'!D16 -> 84118 | C16: ='F BS Assumptions'!C6*'F BS Assumptions'!C17 -> 91149.554 | D16: ='F BS Assumptions'!D6*'F BS Assumptions'!D17 -> 97757.308 | E16: ='F BS Assumptions'!E6*'F BS Assumptions'!E17 -> 104045.48 | F16: ='F BS Assumptions'!F6*'F BS Assumptions'!F17 -> 110120.72 | G16: ='F BS Assumptions'!G6*'F BS Assumptions'!G17 -> 115949.53 | H16: ='F BS Assumptions'!H6*'F BS Assumptions'!H17 -> 121368.11
A17: Property, plant and equipment, net | B17: ='B Balance Sheet'!D17 -> 51431 | C17: ='F BS Assumptions'!C6*'F BS Assumptions'!C18 -> 55730.197 | D17: ='F BS Assumptions'!D6*'F BS Assumptions'!D18 -> 59770.277 | E17: ='F BS Assumptions'!E6*'F BS Assumptions'!E18 -> 63614.959 | F17: ='F BS Assumptions'!F6*'F BS Assumptions'!F18 -> 67329.452 | G17: ='F BS Assumptions'!G6*'F BS Assumptions'!G18 -> 70893.271 | H17: ='F BS Assumptions'!H6*'F BS Assumptions'!H18 -> 74206.272
A18: Non-current intangible assets, net | B18: ='B Balance Sheet'!D18 -> 20342 | C18: ='F BS Assumptions'!C6*'F BS Assumptions'!C19 -> 22042.419 | D18: ='F BS Assumptions'!D6*'F BS Assumptions'!D19 -> 23640.352 | E18: ='F BS Assumptions'!E6*'F BS Assumptions'!E19 -> 25161.002 | F18: ='F BS Assumptions'!F6*'F BS Assumptions'!F19 -> 26630.159 | G18: ='F BS Assumptions'!G6*'F BS Assumptions'!G19 -> 28039.722 | H18: ='F BS Assumptions'!H6*'F BS Assumptions'!H19 -> 29350.08
A19: Other non-current assets | B19: ='B Balance Sheet'!D19 -> 77557 | C19: ='F BS Assumptions'!C6*'F BS Assumptions'!C20 -> 84040.11 | D19: ='F BS Assumptions'!D6*'F BS Assumptions'!D20 -> 90132.475 | E19: ='F BS Assumptions'!E6*'F BS Assumptions'!E20 -> 95930.186 | F19: ='F BS Assumptions'!F6*'F BS Assumptions'!F20 -> 101531.57 | G19: ='F BS Assumptions'!G6*'F BS Assumptions'!G20 -> 106905.75 | H19: ='F BS Assumptions'!H6*'F BS Assumptions'!H20 -> 111901.69
A20: Total non-current assets | B20: ='B Balance Sheet'!D20 -> 233448 | C20: =SUM(C16:C19) -> 252962.28 | D20: =SUM(D16:D19) -> 271300.41 | E20: =SUM(E16:E19) -> 288751.63 | F20: =SUM(F16:F19) -> 305611.9 | G20: =SUM(G16:G19) -> 321788.27 | H20: =SUM(H16:H19) -> 336826.15
A21: Total assets | B21: ='B Balance Sheet'!D21 -> 395361.44 | C21: =C13+C20 -> 427848.91 | D21: =D13+D20 -> 458297.98 | E21: =E13+E20 -> 487179.37 | F21: =F13+F20 -> 515028.1 | G21: =G13+G20 -> 541707.88 | H21: =H13+H20 -> 566501.45
A23: Current liabilities
A24: Accounts payable | B24: ='B Balance Sheet'!D24 -> 76682.867 | C24: ='F BS Assumptions'!C7/'F BS Assumptions'!C21 -> 82204.909 | D24: ='F BS Assumptions'!D7/'F BS Assumptions'!D21 -> 87267.03 | E24: ='F BS Assumptions'!E7/'F BS Assumptions'!E21 -> 91934.034 | F24: ='F BS Assumptions'!F7/'F BS Assumptions'!F21 -> 96356.528 | G24: ='F BS Assumptions'!G7/'F BS Assumptions'!G21 -> 100537.45 | H24: ='F BS Assumptions'!H7/'F BS Assumptions'!H21 -> 104410.67
A25: Other current liabilities | B25: ='B Balance Sheet'!D25 -> 62259 | C25: ='F BS Assumptions'!C6*'F BS Assumptions'!C23 -> 67463.326 | D25: ='F BS Assumptions'!D6*'F BS Assumptions'!D23 -> 72353.982 | E25: ='F BS Assumptions'!E6*'F BS Assumptions'!E23 -> 77008.103 | F25: ='F BS Assumptions'!F6*'F BS Assumptions'!F23 -> 81504.624 | G25: ='F BS Assumptions'!G6*'F BS Assumptions'!G23 -> 85818.75 | H25: ='F BS Assumptions'!H6*'F BS Assumptions'!H23 -> 89829.252
A26: Deferred revenue | B26: ='B Balance Sheet'!D26 -> 10000.392 | C26: ='F BS Assumptions'!C6/'F BS Assumptions'!C22 -> 10836.341 | D26: ='F BS Assumptions'!D6/'F BS Assumptions'!D22 -> 11621.905 | E26: ='F BS Assumptions'!E6/'F BS Assumptions'!E22 -> 12369.477 | F26: ='F BS Assumptions'!F6/'F BS Assumptions'!F22 -> 13091.733 | G26: ='F BS Assumptions'!G6/'F BS Assumptions'!G22 -> 13784.693 | H26: ='F BS Assumptions'!H6/'F BS Assumptions'!H22 -> 14428.882
A27: Commercial paper | B27: ='B Balance Sheet'!D27 -> 1997 | C27: =B27*(1+'F BS Assumptions'!C27) -> 1937.09 | D27: =C27*(1+'F BS Assumptions'!D27) -> 1878.9773 | E27: =D27*(1+'F BS Assumptions'!E27) -> 1822.608 | F27: =E27*(1+'F BS Assumptions'!F27) -> 1767.9297 | G27: =F27*(1+'F BS Assumptions'!G27) -> 1714.8918 | H27: =G27*(1+'F BS Assumptions'!H27) -> 1663.4451
A28: Current term debt | B28: ='B Balance Sheet'!D28 -> 11007 | C28: =B28*(1+'F BS Assumptions'!C27) -> 10676.79 | D28: =C28*(1+'F BS Assumptions'!D27) -> 10356.486 | E28: =D28*(1+'F BS Assumptions'!E27) -> 10045.792 | F28: =E28*(1+'F BS Assumptions'!F27) -> 9744.418 | G28: =F28*(1+'F BS Assumptions'!G27) -> 9452.0854 | H28: =G28*(1+'F BS Assumptions'!H27) -> 9168.5229
A29: Total current liabilities | B29: ='B Balance Sheet'!D29 -> 161946.26 | C29: =SUM(C24:C28) -> 173118.46 | D29: =SUM(D24:D28) -> 183478.38 | E29: =SUM(E24:E28) -> 193180.01 | F29: =SUM(F24:F28) -> 202465.23 | G29: =SUM(G24:G28) -> 211307.87 | H29: =SUM(H24:H28) -> 219500.78
A30: Non-current liabilities
A31: Long-term debt | B31: ='B Balance Sheet'!D31 -> 71340 | C31: =B31*(1+'F BS Assumptions'!C27) -> 69199.8 | D31: =C31*(1+'F BS Assumptions'!D27) -> 67123.806 | E31: =D31*(1+'F BS Assumptions'!E27) -> 65110.092 | F31: =E31*(1+'F BS Assumptions'!F27) -> 63156.789 | G31: =F31*(1+'F BS Assumptions'!G27) -> 61262.085 | H31: =G31*(1+'F BS Assumptions'!H27) -> 59424.223
A32: Other non-current liabilities | B32: ='B Balance Sheet'!D32 -> 55080 | C32: ='F BS Assumptions'!C6*'F BS Assumptions'!C24 -> 59684.223 | D32: ='F BS Assumptions'!D6*'F BS Assumptions'!D24 -> 64010.943 | E32: ='F BS Assumptions'!E6*'F BS Assumptions'!E24 -> 68128.404 | F32: ='F BS Assumptions'!F6*'F BS Assumptions'!F24 -> 72106.438 | G32: ='F BS Assumptions'!G6*'F BS Assumptions'!G24 -> 75923.108 | H32: ='F BS Assumptions'!H6*'F BS Assumptions'!H24 -> 79471.164
A33: Total non-current liabilities | B33: ='B Balance Sheet'!D33 -> 126420 | C33: =SUM(C31:C32) -> 128884.02 | D33: =SUM(D31:D32) -> 131134.75 | E33: =SUM(E31:E32) -> 133238.5 | F33: =SUM(F31:F32) -> 135263.23 | G33: =SUM(G31:G32) -> 137185.19 | H33: =SUM(H31:H32) -> 138895.39
A34: Total liabilities | B34: ='B Balance Sheet'!D34 -> 288366.26 | C34: =C29+C33 -> 302002.48 | D34: =D29+D33 -> 314613.13 | E34: =E29+E33 -> 326418.51 | F34: =F29+F33 -> 337728.46 | G34: =G29+G33 -> 348493.07 | H34: =H29+H33 -> 358396.16
A35: Shareholders equity
A36: Common stock and additional paid-in capital | B36: ='B Balance Sheet'!D36 -> 101897 | C36: =B36 -> 101897 | D36: =C36 -> 101897 | E36: =D36 -> 101897 | F36: =E36 -> 101897 | G36: =F36 -> 101897 | H36: =G36 -> 101897
A37: Retained earnings / accumulated deficit | B37: ='B Balance Sheet'!D37 -> 9606.1794 | C37: =B37+C48-C49-C51 -> 28457.437 | D37: =C37+D48-D49-D51 -> 46295.85 | E37: =D37+E48-E49-E51 -> 63371.865 | F37: =E37+F48-F49-F51 -> 79910.644 | G37: =F37+G48-G49-G51 -> 95825.815 | H37: =G37+H48-H49-H51 -> 110716.29
A38: Accumulated other comprehensive loss | B38: ='B Balance Sheet'!D38 -> -4508 | C38: =B38 -> -4508 | D38: =C38 -> -4508 | E38: =D38 -> -4508 | F38: =E38 -> -4508 | G38: =F38 -> -4508 | H38: =G38 -> -4508
A39: Total shareholders equity | B39: ='B Balance Sheet'!D39 -> 106995.18 | C39: =SUM(C36:C38) -> 125846.44 | D39: =SUM(D36:D38) -> 143684.85 | E39: =SUM(E36:E38) -> 160760.86 | F39: =SUM(F36:F38) -> 177299.64 | G39: =SUM(G36:G38) -> 193214.81 | H39: =SUM(H36:H38) -> 208105.29
A40: Total liabilities and shareholders equity | B40: ='B Balance Sheet'!D40 -> 395361.44 | C40: =C34+C39 -> 427848.91 | D40: =D34+D39 -> 458297.98 | E40: =E34+E39 -> 487179.37 | F40: =F34+F39 -> 515028.1 | G40: =G34+G39 -> 541707.88 | H40: =H34+H39 -> 566501.45
A47: Capital allocation and audit
A48: Net income | B48: ='E IS Outputs for BS'!B10 -> 130566.18 | C48: ='E IS Outputs for BS'!C10 -> 145364.77 | D48: ='E IS Outputs for BS'!D10 -> 159222.98 | E48: ='E IS Outputs for BS'!E10 -> 172975.9 | F48: ='E IS Outputs for BS'!F10 -> 186642.39 | G48: ='E IS Outputs for BS'!G10 -> 200073.26 | H48: ='E IS Outputs for BS'!H10 -> 212774.86
A49: Dividends declared | B49: ='F BS Assumptions'!B29 -> 15731 | C49: =B49*(1+'F BS Assumptions'!C28) -> 16202.93 | D49: =C49*(1+'F BS Assumptions'!D28) -> 16689.018 | E49: =D49*(1+'F BS Assumptions'!E28) -> 17189.688 | F49: =E49*(1+'F BS Assumptions'!F28) -> 17705.379 | G49: =F49*(1+'F BS Assumptions'!G28) -> 18236.54 | H49: =G49*(1+'F BS Assumptions'!H28) -> 18783.637
A50: Target ending retained earnings | B50: =B37 -> 9606.1794 | C50: =C21-C34-C36-C38 -> 28457.437 | D50: =D21-D34-D36-D38 -> 46295.85 | E50: =E21-E34-E36-E38 -> 63371.865 | F50: =F21-F34-F36-F38 -> 79910.644 | G50: =G21-G34-G36-G38 -> 95825.815 | H50: =H21-H34-H36-H38 -> 110716.29
A51: Share repurchases: cash sweep | B51: ='F BS Assumptions'!B30 -> 88191 | C51: =B37+C48-C49-C50 -> 110310.59 | D51: =C37+D48-D49-D50 -> 124695.54 | E51: =D37+E48-E49-E50 -> 138710.2 | F51: =E37+F48-F49-F50 -> 152398.24 | G51: =F37+G48-G49-G50 -> 165921.55 | H51: =G37+H48-H49-H50 -> 179100.74
A52: Implied average buyback price (USD/share) | C52: =C51/('C2 Annual IS Forecast'!G32-'C2 Annual IS Forecast'!H32) -> 374.56326 | D52: =D51/('C2 Annual IS Forecast'!H32-'C2 Annual IS Forecast'!I32) -> 432.04885 | E52: =E51/('C2 Annual IS Forecast'!I32-'C2 Annual IS Forecast'!J32) -> 490.41555 | F52: =F51/('C2 Annual IS Forecast'!J32-'C2 Annual IS Forecast'!K32) -> 549.80629 | G52: =G51/('C2 Annual IS Forecast'!K32-'C2 Annual IS Forecast'!L32) -> 610.81047 | H52: =H51/('C2 Annual IS Forecast'!L32-'C2 Annual IS Forecast'!M32) -> 672.78299
A53: Flow to equity / distributions | B53: =B49+B51 -> 103922 | C53: =C49+C51 -> 126513.52 | D53: =D49+D51 -> 141384.56 | E53: =E49+E51 -> 155899.89 | F53: =F49+F51 -> 170103.61 | G53: =G49+G51 -> 184158.09 | H53: =H49+H51 -> 197884.38
A54: Clean-surplus difference | C54: =C39-B39-C48+C53 -> 0 | D54: =D39-C39-D48+D53 -> 0 | E54: =E39-D39-E48+E53 -> 0 | F54: =F39-E39-F48+F53 -> 0 | G54: =G39-F39-G48+G53 -> 0 | H54: =H39-G39-H48+H53 -> 0
A55: Balance sheet difference | B55: =B21-B40 -> 0 | C55: =ROUND(C21-C40,2) -> 0 | D55: =ROUND(D21-D40,2) -> 0 | E55: =ROUND(E21-E40,2) -> 0 | F55: =ROUND(F21-F40,2) -> 0 | G55: =ROUND(G21-G40,2) -> 0 | H55: =ROUND(H21-H40,2) -> 0
A56: Cash and repurchase status | C56: =IF(C7<=0,"Negative cash",IF(C51<0,"Negative repurchases",IF(ABS(C55)>0.005,"Out of balance","OK"))) -> OK | D56: =IF(D7<=0,"Negative cash",IF(D51<0,"Negative repurchases",IF(ABS(D55)>0.005,"Out of balance","OK"))) -> OK | E56: =IF(E7<=0,"Negative cash",IF(E51<0,"Negative repurchases",IF(ABS(E55)>0.005,"Out of balance","OK"))) -> OK | F56: =IF(F7<=0,"Negative cash",IF(F51<0,"Negative repurchases",IF(ABS(F55)>0.005,"Out of balance","OK"))) -> OK | G56: =IF(G7<=0,"Negative cash",IF(G51<0,"Negative repurchases",IF(ABS(G55)>0.005,"Out of balance","OK"))) -> OK | H56: =IF(H7<=0,"Negative cash",IF(H51<0,"Negative repurchases",IF(ABS(H55)>0.005,"Out of balance","OK"))) -> OK
A58: Interest-bearing debt / ending equity | B58: =SUM(B27:B28,B31)/B39 -> 0.7882972 | C58: =SUM(C27:C28,C31)/C39 -> 0.65010724 | D58: =SUM(D27:D28,D31)/D39 -> 0.5523148 | E58: =SUM(E27:E28,E31)/E39 -> 0.4788385 | F58: =SUM(F27:F28,F31)/F39 -> 0.42114657 | G58: =SUM(G27:G28,G31)/G39 -> 0.37486288 | H58: =SUM(H27:H28,H31)/H39 -> 0.33759925
A59: Annual sales / ending assets | B59: ='E IS Outputs for BS'!B6/B21 -> 1.2078088 | C59: ='E IS Outputs for BS'!C6/C21 -> 1.2093936 | D59: ='E IS Outputs for BS'!D6/D21 -> 1.2108904 | E59: ='E IS Outputs for BS'!E6/E21 -> 1.2123776 | F59: ='E IS Outputs for BS'!F6/F21 -> 1.2137847 | G59: ='E IS Outputs for BS'!G6/G21 -> 1.215087 | H59: ='E IS Outputs for BS'!H6/H21 -> 1.2162059
A60: COGS / ending inventory | B60: ='E IS Outputs for BS'!B7/B11 -> 20.315628 | C60: ='E IS Outputs for BS'!C7/C11 -> 20.315628 | D60: ='E IS Outputs for BS'!D7/D11 -> 20.315628 | E60: ='E IS Outputs for BS'!E7/E11 -> 20.315628 | F60: ='E IS Outputs for BS'!F7/F11 -> 20.315628 | G60: ='E IS Outputs for BS'!G7/G11 -> 20.315628 | H60: ='E IS Outputs for BS'!H7/H11 -> 20.315628
A61: COGS / ending A/P | B61: ='E IS Outputs for BS'!B7/B24 -> 3.1947959 | C61: ='E IS Outputs for BS'!C7/C24 -> 3.1947959 | D61: ='E IS Outputs for BS'!D7/D24 -> 3.1947959 | E61: ='E IS Outputs for BS'!E7/E24 -> 3.1947959 | F61: ='E IS Outputs for BS'!F7/F24 -> 3.1947959 | G61: ='E IS Outputs for BS'!G7/G24 -> 3.1947959 | H61: ='E IS Outputs for BS'!H7/H24 -> 3.1947959
A63: Annual ratio basis: FY2026 full-year flows divided by the FY2026 Q4 ending balance; later years use year-end balances.
A64: Buybacks are a residual distribution needed to maintain the cash target; this is a forecast policy, not announced company guidance.

Sheet H Flow to Equity
A2: Discounted Flow to Equity
A3: USD millions except per-share values; valuation date is FY2026 fiscal year-end.
A5: Metric | B5: FY2026 Base | C5: FY2027 Forecast | D5: FY2028 Forecast | E5: FY2029 Forecast | F5: FY2030 Forecast | G5: FY2031 Forecast | H5: FY2032 Forecast | J5: Valuation assumption | K5: Value | L5: Basis
A6: Net income | C6: ='G Annual BS Forecast'!C48 -> 145364.77 | D6: ='G Annual BS Forecast'!D48 -> 159222.98 | E6: ='G Annual BS Forecast'!E48 -> 172975.9 | F6: ='G Annual BS Forecast'!F48 -> 186642.39 | G6: ='G Annual BS Forecast'!G48 -> 200073.26 | H6: ='G Annual BS Forecast'!H48 -> 212774.86 | J6: Cost of equity | K6: 0.08 | L6: Specified in Group Project Task 3.
A7: Opening common equity | C7: ='G Annual BS Forecast'!B39 -> 106995.18 | D7: ='G Annual BS Forecast'!C39 -> 125846.44 | E7: ='G Annual BS Forecast'!D39 -> 143684.85 | F7: ='G Annual BS Forecast'!E39 -> 160760.86 | G7: ='G Annual BS Forecast'!F39 -> 177299.64 | H7: ='G Annual BS Forecast'!G39 -> 193214.81 | J7: Terminal growth rate | K7: 0.03 | L7: Assumed steady nominal equity-flow and book-equity growth after FY2032.
A8: Closing common equity | B8: ='G Annual BS Forecast'!B39 -> 106995.18 | C8: ='G Annual BS Forecast'!C39 -> 125846.44 | D8: ='G Annual BS Forecast'!D39 -> 143684.85 | E8: ='G Annual BS Forecast'!E39 -> 160760.86 | F8: ='G Annual BS Forecast'!F39 -> 177299.64 | G8: ='G Annual BS Forecast'!G39 -> 193214.81 | H8: ='G Annual BS Forecast'!H39 -> 208105.29 | J8: Valuation shares (million) | K8: ='A1 Income Statement'!F30 -> 14650 | L8: Q4 FY2026 forecast diluted weighted-average shares; proxy for valuation-date share count.
A9: Change in common equity | C9: =C8-C7 -> 18851.257 | D9: =D8-D7 -> 17838.413 | E9: =E8-E7 -> 17076.015 | F9: =F8-F7 -> 16538.779 | G9: =G8-G7 -> 15915.171 | H9: =H8-H7 -> 14890.475 | J9: AAPL regular-session close | K9: 332.89 | L9: Oct 5, 2026 US close; StockAnalysis.com.
A10: Flow to equity (NI - change in equity) | C10: =C6-C9 -> 126513.52 | D10: =D6-D9 -> 141384.56 | E10: =E6-E9 -> 155899.89 | F10: =F6-F9 -> 170103.61 | G10: =G6-G9 -> 184158.09 | H10: =H6-H9 -> 197884.38 | J10: Market price date | K10: 2026-10-05 US close
A11: Dividends | C11: ='G Annual BS Forecast'!C49 -> 16202.93 | D11: ='G Annual BS Forecast'!D49 -> 16689.018 | E11: ='G Annual BS Forecast'!E49 -> 17189.688 | F11: ='G Annual BS Forecast'!F49 -> 17705.379 | G11: ='G Annual BS Forecast'!G49 -> 18236.54 | H11: ='G Annual BS Forecast'!H49 -> 18783.637
A12: Share repurchases | C12: ='G Annual BS Forecast'!C51 -> 110310.59 | D12: ='G Annual BS Forecast'!D51 -> 124695.54 | E12: ='G Annual BS Forecast'!E51 -> 138710.2 | F12: ='G Annual BS Forecast'!F51 -> 152398.24 | G12: ='G Annual BS Forecast'!G51 -> 165921.55 | H12: ='G Annual BS Forecast'!H51 -> 179100.74
A13: Distribution consistency difference | C13: =ROUND(C10-C11-C12,2) -> 0 | D13: =ROUND(D10-D11-D12,2) -> 0 | E13: =ROUND(E10-E11-E12,2) -> 0 | F13: =ROUND(F10-F11-F12,2) -> 0 | G13: =ROUND(G10-G11-G12,2) -> 0 | H13: =ROUND(H10-H11-H12,2) -> 0
A14: Discount factor | C14: =1/(1+$K$6)^1 -> 0.92592593 | D14: =1/(1+$K$6)^2 -> 0.85733882 | E14: =1/(1+$K$6)^3 -> 0.79383224 | F14: =1/(1+$K$6)^4 -> 0.73502985 | G14: =1/(1+$K$6)^5 -> 0.6805832 | H14: =1/(1+$K$6)^6 -> 0.63016963 | J14: FY2033 normalized net income | K14: =H6*(1+$K$7) -> 219158.1
A15: Present value of flow to equity | C15: =C10*C14 -> 117142.14 | D15: =D10*D14 -> 121214.47 | E15: =E10*E14 -> 123758.36 | F15: =F10*F14 -> 125031.24 | G15: =G10*G14 -> 125334.9 | H15: =H10*H14 -> 124700.73 | J15: FY2033 sustainable equity growth | K15: =H8*$K$7 -> 6243.1587
J16: FY2033 sustainable FTE | K16: =K14-K15 -> 212914.94
J17: Terminal value at FY2032 | K17: =K16/($K$6-$K$7) -> 4258298.9
J18: Present value of terminal value | K18: =K17*H14 -> 2683450.6
J19: PV of FY2027-FY2032 FTE | K19: =SUM(C15:H15) -> 737181.84
J20: Equity value | K20: =K18+K19 -> 3420632.5
J21: Value per share | K21: =K20/$K$8 -> 233.49027
J22: Upside / (downside) | K22: =K21/$K$9-1 -> -0.29859632
J23: Terminal value share of total | K23: =K18/K20 -> 0.78448961
A26: Terminal growth sensitivity
J27: Terminal growth | K27: FTE value / share
J28: 0.02 | K28: =($K$19+(H6*(1+J28)-H8*J28)/($K$6-J28)*H14)/$K$8 -> 202.92834
J29: 0.03 | K29: =($K$19+(H6*(1+J29)-H8*J29)/($K$6-J29)*H14)/$K$8 -> 233.49027
J30: 0.04 | K30: =($K$19+(H6*(1+J30)-H8*J30)/($K$6-J30)*H14)/$K$8 -> 279.33316
J32: Method note | L32: FTE equals net income less the increase in common book equity. In this clean-surplus model it also equals dividends plus cash-sweep repurchases.
J33: Terminal note | L33: FY2033 net income and book equity growth normalize immediately to the stated terminal rate; this is a material valuation assumption.
J34: Market source | L34: https://stockanalysis.com/stocks/aapl/statistics/

Sheet I Residual Income
A2: Residual Income to Common Equity
A3: USD millions except per-share values; same 8% cost of equity and terminal growth as the FTE model.
A5: Metric | B5: FY2026 Base | C5: FY2027 Forecast | D5: FY2028 Forecast | E5: FY2029 Forecast | F5: FY2030 Forecast | G5: FY2031 Forecast | H5: FY2032 Forecast | I5: 2033
A6: Net income | C6: ='G Annual BS Forecast'!C48 -> 145364.77 | D6: ='G Annual BS Forecast'!D48 -> 159222.98 | E6: ='G Annual BS Forecast'!E48 -> 172975.9 | F6: ='G Annual BS Forecast'!F48 -> 186642.39 | G6: ='G Annual BS Forecast'!G48 -> 200073.26 | H6: ='G Annual BS Forecast'!H48 -> 212774.86 | I6: =K14 -> 219158.1
A7: Opening common equity | C7: ='G Annual BS Forecast'!B39 -> 106995.18 | D7: ='G Annual BS Forecast'!C39 -> 125846.44 | E7: ='G Annual BS Forecast'!D39 -> 143684.85 | F7: ='G Annual BS Forecast'!E39 -> 160760.86 | G7: ='G Annual BS Forecast'!F39 -> 177299.64 | H7: ='G Annual BS Forecast'!G39 -> 193214.81 | I7: ='G Annual BS Forecast'!H39 -> 208105.29
A8: Equity charge at 8% | C8: =C7*'H Flow to Equity'!$K$6 -> 8559.6144 | D8: =D7*'H Flow to Equity'!$K$6 -> 10067.715 | E8: =E7*'H Flow to Equity'!$K$6 -> 11494.788 | F8: =F7*'H Flow to Equity'!$K$6 -> 12860.869 | G8: =G7*'H Flow to Equity'!$K$6 -> 14183.972 | H8: =H7*'H Flow to Equity'!$K$6 -> 15457.185 | I8: =K15 -> 16648.423
A9: Residual income | C9: =C6-C8 -> 136805.16 | D9: =D6-D8 -> 149155.26 | E9: =E6-E8 -> 161481.11 | F9: =F6-F8 -> 173781.53 | G9: =G6-G8 -> 185889.29 | H9: =H6-H8 -> 197317.67 | I9: =I6-I8 -> 202509.68
A10: Discount factor | C10: ='H Flow to Equity'!C14 -> 0.92592593 | D10: ='H Flow to Equity'!D14 -> 0.85733882 | E10: ='H Flow to Equity'!E14 -> 0.79383224 | F10: ='H Flow to Equity'!F14 -> 0.73502985 | G10: ='H Flow to Equity'!G14 -> 0.6805832 | H10: ='H Flow to Equity'!H14 -> 0.63016963 | I10: TV: | J10: =K17 -> 4050193.6
A11: Present value of residual income | C11: =C9*C10 -> 126671.44 | D11: =D9*D10 -> 127876.6 | E11: =E9*E10 -> 128188.91 | F11: =F9*F10 -> 127734.61 | G11: =G9*G10 -> 126513.12 | H11: =H9*H10 -> 124343.6 | I11: PV: | J11: =K18 -> 2552309
G12: sum | H12: =sum(C11:H11) -> 761328.29
J14: FY2033 normalized net income | K14: ='H Flow to Equity'!K14 -> 219158.1
J15: FY2033 equity charge | K15: ='G Annual BS Forecast'!H39*'H Flow to Equity'!K6 -> 16648.423
J16: FY2033 residual income | K16: =K14-K15 -> 202509.68
J17: Terminal value of residual income | K17: =K16/('H Flow to Equity'!K6-'H Flow to Equity'!K7) -> 4050193.6
J18: Present value of terminal RI | K18: =K17*'H Flow to Equity'!H14 -> 2552309
J19: PV of FY2027-FY2032 RI | K19: =SUM(C11:H11) -> 761328.29
J20: FY2026 closing common equity | K20: ='G Annual BS Forecast'!B39 -> 106995.18
J21: Equity value | K21: =SUM(K18:K20) -> 3420632.5
J22: Value per share | K22: =K21/'H Flow to Equity'!K8 -> 233.49027
J23: Difference from FTE value | K23: =K21-'H Flow to Equity'!K20 -> 0
J26: Identity note | L26: The two absolute methods match because forecast common equity follows clean surplus and the same FY2033 net income/book-equity terminal bridge is used.
J27: Class formula source | L27: ACC3705 Equity 4/5 lecture notes: RI = NI - 8% x beginning common equity; value = beginning common equity + PV of RI.

Sheet J Relative Valuation
A2: Relative Valuation - Guideline Companies
A3: Forward multiples captured 2026-10-06 Singapore after the Oct 5 US regular-session close; Forward P/E is applied to FY2027 earnings, while EV/EBIT is applied to FY2026 EBIT to maintain consistency with its current/trailing basis.
A5: Guideline Companies | B5: Ticker | C5: Forward P/E | D5: EV/EBIT | E5: Selection rationale | F5: Source
A6: Microsoft | B6: MSFT | C6: 26.77 | D6: 25.65 | E6: Large integrated device, software and subscription ecosystem; stronger enterprise mix. | F6: https://stockanalysis.com/stocks/msft/statistics/
A7: Alphabet | B7: GOOGL | C7: 25.89 | D7: 27.98 | E7: Mobile ecosystem, app distribution, digital services and advertising; less hardware. | F7: https://stockanalysis.com/stocks/googl/statistics/
A8: Meta Platforms | B8: META | C8: 22.97 | D8: 21.91 | E8: Consumer platform, mobile engagement, digital monetization and AI investment; ad-heavy. | F8: https://stockanalysis.com/stocks/meta/statistics/
A9: Samsung Electronics | C9: 4.4 | D9: 8.75 | E9: A strong operating comparable given its direct competition with Apple in smartphones and consumer electronics | F9: Samsung Electronics (KRX:005930) Financial Ratios
A10: Sony Group | B10: SONY | C10: 17.65 | D10: 13.14 | E10: combines branded hardware with digital content and services | F10: Sony Group (SONY) Financial Ratios
A11: Peer median | C11: =MEDIAN(C6:C10) -> 22.97 | D11: =MEDIAN(D6:D10) -> 21.91
A13: Year | B13: Apple Forward P/E | C13: Peer Median Forward P/E | D13: Apple Premium | E13: Apple EV/EBIT | F13: Peer Median EV/EBIT | G13: Apple Premium | H13: Source: MorningStar
A14: 2021 | B14: 31.6 | C14: 20.1 | D14: =B14/C14-1 -> 0.5721393 | E14: 27.4 | F14: 18.88 | G14: =E14/F14-1 -> 0.45127119
A15: 2022 | B15: 21.28 | C15: 15.04 | D15: =B15/C15-1 -> 0.41489362 | E15: 18.04 | F15: 11.31 | G15: =E15/F15-1 -> 0.59504863
A16: 2023 | B16: 29.19 | C16: 20.95 | D16: =B16/C16-1 -> 0.39331742 | E16: 26.83 | F16: 23.34 | G16: =E16/F16-1 -> 0.14952871
A17: 2024 | B17: 33.66 | C17: 18.16 | D17: =B17/C17-1 -> 0.85352423 | E17: 30.99 | F17: 20.95 | G17: =E17/F17-1 -> 0.47923628
A18: 2025 | B18: 32.79 | C18: 20.03 | D18: =B18/C18-1 -> 0.63704443 | E18: 30.6 | F18: 21.55 | G18: =E18/F18-1 -> 0.4199536
A19: 5-year average premium | D19: =AVERAGE(D14:D18) -> 0.5741838 | G19: =AVERAGE(G14:G18) -> 0.41900768
A21: Apply peer multiples to Apple
A22: Apple FY2027 net income | B22: ='C2 Annual IS Forecast'!H30 -> 145364.77
A23: FY2027 diluted shares (million) | B23: ='C2 Annual IS Forecast'!H32 -> 14430.723
A24: P/E implied equity value | B24: =C11*B22 -> 3339028.8
A25: Forward P/E historical premium | B25: =D19 -> 0.5741838
A26: P/E fair value per share | B26: =(B24/B23)*(1+B25) -> 364.2399
A27: EV/EBIT historical premium | B27: =G19 -> 0.41900768
A28: Target EV/EBIT | B28: =D11*(1+B27) -> 31.090458
A29: Apple FY2026 EBIT | B29: ='C2 Annual IS Forecast'!G22 -> 156934.91
A30: EV/EBIT implied equity value (premium) | B30: =B28*B29 +'G Annual BS Forecast'!B7 +'G Annual BS Forecast'!B8 +'G Annual BS Forecast'!B16 -'G Annual BS Forecast'!B27 -'G Annual BS Forecast'!B28 -'G Annual BS Forecast'!B31 -> 4931036.2
A31: EV/EBIT fair value per share | B31: =B30/'C2 Annual IS Forecast'!F32 -> 336.5895
A32: AAPL Oct 5 close | B32: ='H Flow to Equity'!K9 -> 332.89
A33: P/E upside / (downside) | B33: =B26/B32-1 -> 0.094174953
A34: EV/EBIT upside / (downside) | B34: =B31/B32-1 -> 0.011113293
A36: Multiple choice and comparability
A37: Forward P/E | E37: Directly capitalizes FY2027 expected net income; useful because Apple and all five peers have positive earnings.
A38: EV/EBIT | E38: EV/EBIT provides a capital-structure-neutral measure of operating value, and depreciation and amortization are relatively modest for Apple
A39: Why not P/B | E39: Apple's book equity is materially affected by its long-running share repurchase programme and does not fully reflect internally generated intangible assets such as its brand and ecosystem.
A40: Peer limitation | E40: No listed company matches Apple device, software and services mix. The cross-sector median reduces, but does not remove, business-mix bias.
A41: Vendor caveat | E41: Forward ratios are published vendor figures, not independently recomputed next-twelve-month analyst estimates; numerator/denominator definitions can differ.
A44: Historical Peer Forward P/E
A45: Year | B45: MSFT | C45: GOOG | D45: META | E45: Samsung | F45: Sony | G45: Peer median
A46: 2021 | B46: 36.96 | C46: 21.08 | D46: 19.86 | E46: 11.93 | F46: 20.1 | G46: =MEDIAN(B46:F46) -> 20.1
A47: 2022 | B47: 25.22 | C47: 16.6 | D47: 15.04 | E47: 14.32 | F47: 13.03 | G47: =MEDIAN(B47:F47) -> 15.04
A48: 2023 | B48: 33.64 | C48: 21.13 | D48: 20.76 | E48: n.a. | F48: 16.06 | G48: =MEDIAN(B48:F48) -> 20.945
A49: 2024 | B49: 32.02 | C49: 18.16 | D49: 20.76 | E49: 9.41 | F49: 16.72 | G49: =MEDIAN(B49:F49) -> 18.16
A50: 2025 | B50: 30.41 | C50: 24.48 | D50: 20.03 | E50: 10.61 | F50: 18.75 | G50: =MEDIAN(B50:F50) -> 20.03
A53: Historical Peer EV/EBIT
A54: Year | B54: MSFT | C54: GOOG | D54: META | E54: Samsung | F54: Sony | G54: Peer median
A55: 2021 | B55: 32.46 | C55: 21.57 | D55: 18.88 | E55: 9.2 | F55: 14.9 | G55: =MEDIAN(B55:F55) -> 18.88
A56: 2022 | B56: 20.58 | C56: 13.72 | D56: 8.56 | E56: 4.87 | F56: 11.31 | G56: =MEDIAN(B56:F56) -> 11.31
A57: 2023 | B57: 29.26 | C57: 22.09 | D57: 24.58 | E57: n.a. | F57: 17.58 | G57: =MEDIAN(B57:F57) -> 23.335
A58: 2024 | B58: 28.06 | C58: 20.95 | D58: 23.43 | E58: 9.46 | F58: 14.46 | G58: =MEDIAN(B58:F58) -> 20.95
A59: 2025 | B59: 27.93 | C59: 25.07 | D59: 20.16 | E59: 21.55 | F59: 15.58 | G59: =MEDIAN(B59:F59) -> 21.55
A62: Company | B62: Source
A63: Apple | B63: https://www.morningstar.com/stocks/xnas/aapl/valuation
A64: Microsoft | B64: https://www.morningstar.com/stocks/xnas/msft/valuation
A65: Alphabet Class C | B65: https://www.morningstar.com/stocks/xnas/goog/valuation
A66: Meta | B66: https://www.morningstar.com/stocks/xnas/meta/valuation
A67: Samsung | B67: https://www.morningstar.com/stocks/xkrx/005930/valuation
A68: Sony | B68: https://www.morningstar.com/stocks/xnys/sony/valuation
A70: Historical Alphabet multiples use Class C (GOOG), while current multiples use Class A (GOOGL).
A71: Samsung’s 2023 multiples are unavailable; the 2023 peer medians therefore use the other four companies.

Sheet K Valuation Summary
A2: Apple Valuation Summary - FY2026 Year-End
A3: Academic base case; intrinsic values in USD/share. Market comparison uses the Oct 5, 2026 US close.
A5: Approach | B5: Fair value / share | C5: Vs. market price | D5: Equity value (USD m) | E5: What drives the result
A6: Discounted flow to equity | B6: ='H Flow to Equity'!K21 -> 233.49027 | C6: ='H Flow to Equity'!K22 -> -0.29859632 | D6: ='H Flow to Equity'!K20 -> 3420632.5 | E6: 8% cost of equity; 3% terminal growth; buybacks cash sweep.
A7: Residual income | B7: ='I Residual Income'!K22 -> 233.49027 | C7: =B7/$B$11-1 -> -0.29859632 | D7: ='I Residual Income'!K21 -> 3420632.5 | E7: Clean-surplus book equity plus discounted residual income.
A8: Peer forward P/E | B8: ='J Relative Valuation'!B26 -> 364.2399 | C8: =B8/$B$11-1 -> 0.094174953 | D8: ='J Relative Valuation'!B24*(1+'J Relative Valuation'!B25) -> 5256245.1 | E8: Peer median forward P/E adjusted for Apple’s historical valuation premium and applied to FY2027 earnings.
A9: Peer EV/EBIT | B9: ='J Relative Valuation'!B31 -> 336.5895 | C9: =B9/$B$11-1 -> 0.011113293 | D9: ='J Relative Valuation'!B30 -> 4931036.2 | E9: Peer median EV/EBIT adjusted for Apple's historical premium, applied to FY2026 EBIT and converted to equity value using FY2026 year-end net cash and debt.
A11: AAPL market price | B11: ='H Flow to Equity'!K9 -> 332.89 | E11: US regular-session close on Oct 5, 2026; nine days after FY2026 forecast fiscal year-end.
A12: Illustrative stance | B12: =IF(MAX(B6:B9)<B11,"SELL",IF(MIN(B6:B9)>B11,"BUY","HOLD")) -> HOLD | E12: Mechanical comparison for the coursework; not a standalone investment instruction.
A15: Value drivers and diagnostic ratios
A16: FY2026 annual sales | B16: ='C2 Annual IS Forecast'!G9 -> 477521.02
A17: FY2032 annual sales | B17: ='C2 Annual IS Forecast'!M9 -> 688982.42
A18: FY2032 net margin | B18: ='C2 Annual IS Forecast'!M31 -> 0.3088248
A19: FY2026 ending debt / equity | B19: ='G Annual BS Forecast'!B58 -> 0.7882972
A20: FY2032 ending debt / equity | B20: ='G Annual BS Forecast'!H58 -> 0.33759925
A21: Peer median forward P/E | B21: ='J Relative Valuation'!C11 -> 22.97
A22: AAPL quoted forward P/E | B22: 36.17
A23: Peer median forward EV/EBIT | B23: ='J Relative Valuation'!D11 -> 21.91
A24: AAPL quoted EV/EBIT | B24: 31.68
A25: FTE terminal value weight | B25: ='H Flow to Equity'!K23 -> 0.78448961
A28: Interpretation and key limitations
A29: Market premium | E29: Apple currently trades at 36.17x quoted forward earnings versus a 22.97x selected-peer median. This explains much of the peer-valuation gap.
A30: Absolute-method assumptions | E30: The 8% required cost of equity and 3% terminal growth set the long-run capitalization rate. A different growth assumption materially changes the result.
A31: Terminal bridge | E31: Forecast FY2032 growth has not completely converged to 3%; FY2033 is normalized to 3% in the terminal calculation.
A32: Cash and distributions | E32: Annual buybacks are a residual amount that holds cash at a constant sales ratio. They are a model policy, not an announced Apple program.
A33: Share denominator | E33: Forward P/E uses FY2027 forecast diluted EPS, while EV/EBIT uses FY2026 Q4 forecast diluted weighted-average shares as a proxy for valuation-date shares because actual FY2026 year-end basic shares are not yet available.
A34: Market timing | E34: Valuation is at FY2026 fiscal year-end; the comparison price is the latest prior US close at the time of preparation, Oct 5, 2026.
A35: Source links | E35: Apple filings and the supplied forecast are in the original tabs; peer and market sources are linked on J Relative Valuation and H Flow to Equity.

Sheet L Market Comparison
A1: L. Q9 Valuation vs Market: assumptions check, market implied rates and benchmarks
A2: Black = formula; green = link to another worksheet in this file; blue = external input (source in column C or D). USD millions unless stated.
A4: 1. Model inputs (linked to H Flow to Equity)
A6: Fiscal year | B6: t | C6: Net income | D6: Opening common equity
A7: FY2027 | B7: 1 | C7: ='H Flow to Equity'!C6 -> 145364.77 | D7: ='H Flow to Equity'!C7 -> 106995.18
A8: FY2028 | B8: 2 | C8: ='H Flow to Equity'!D6 -> 159222.98 | D8: ='H Flow to Equity'!D7 -> 125846.44
A9: FY2029 | B9: 3 | C9: ='H Flow to Equity'!E6 -> 172975.9 | D9: ='H Flow to Equity'!E7 -> 143684.85
A10: FY2030 | B10: 4 | C10: ='H Flow to Equity'!F6 -> 186642.39 | D10: ='H Flow to Equity'!F7 -> 160760.86
A11: FY2031 | B11: 5 | C11: ='H Flow to Equity'!G6 -> 200073.26 | D11: ='H Flow to Equity'!G7 -> 177299.64
A12: FY2032 | B12: 6 | C12: ='H Flow to Equity'!H6 -> 212774.86 | D12: ='H Flow to Equity'!H7 -> 193214.81
A13: FY2032 closing common equity | D13: ='H Flow to Equity'!H8 -> 208105.29
A15: Valuation shares (million) | B15: ='H Flow to Equity'!K8 -> 14650
A16: AAPL close, 5 Oct 2026 (USD) | B16: ='H Flow to Equity'!K9 -> 332.89
A17: Cost of equity (given in project brief) | B17: ='H Flow to Equity'!K6 -> 0.08
A18: Terminal growth (group assumption) | B18: ='H Flow to Equity'!K7 -> 0.03
A20: 2. Residual income value per share (equals FTE under clean surplus)
A21: Value per share at base cost of equity and growth | B21: =($D$7+SUMPRODUCT(($C$7:$C$12-$B$17*$D$7:$D$12)/(1+$B$17)^$B$7:$B$12)+($C$12*(1+$B$18)-$B$17*$D$13)/($B$17-$B$18)/(1+$B$17)^6)/$B$15 -> 233.49027 | C21: ='K Valuation Summary'!B6 -> 233.49027 | D21: Check: agrees with K Valuation Summary B6
A22: vs market price | B22: =B21/$B$16-1 -> -0.29859632
A24: 3. Sensitivity of value per share (USD)
A25: Cost of equity (rows) / terminal growth (columns) | B25: 0.025 | C25: 0.03 | D25: 0.035 | E25: 0.04
A26: 0.075 | B26: =($D$7+SUMPRODUCT(($C$7:$C$12-$A26*$D$7:$D$12)/(1+$A26)^$B$7:$B$12)+($C$12*(1+B$25)-$A26*$D$13)/($A26-B$25)/(1+$A26)^6)/$B$15 -> 239.47496 | C26: =($D$7+SUMPRODUCT(($C$7:$C$12-$A26*$D$7:$D$12)/(1+$A26)^$B$7:$B$12)+($C$12*(1+C$25)-$A26*$D$13)/($A26-C$25)/(1+$A26)^6)/$B$15 -> 260.42253 | D26: =($D$7+SUMPRODUCT(($C$7:$C$12-$A26*$D$7:$D$12)/(1+$A26)^$B$7:$B$12)+($C$12*(1+D$25)-$A26*$D$13)/($A26-D$25)/(1+$A26)^6)/$B$15 -> 286.60699 | E26: =($D$7+SUMPRODUCT(($C$7:$C$12-$A26*$D$7:$D$12)/(1+$A26)^$B$7:$B$12)+($C$12*(1+E$25)-$A26*$D$13)/($A26-E$25)/(1+$A26)^6)/$B$15 -> 320.27273
A27: 0.08 | B27: =($D$7+SUMPRODUCT(($C$7:$C$12-$A27*$D$7:$D$12)/(1+$A27)^$B$7:$B$12)+($C$12*(1+B$25)-$A27*$D$13)/($A27-B$25)/(1+$A27)^6)/$B$15 -> 216.82013 | C27: =($D$7+SUMPRODUCT(($C$7:$C$12-$A27*$D$7:$D$12)/(1+$A27)^$B$7:$B$12)+($C$12*(1+C$25)-$A27*$D$13)/($A27-C$25)/(1+$A27)^6)/$B$15 -> 233.49027 | D27: =($D$7+SUMPRODUCT(($C$7:$C$12-$A27*$D$7:$D$12)/(1+$A27)^$B$7:$B$12)+($C$12*(1+D$25)-$A27*$D$13)/($A27-D$25)/(1+$A27)^6)/$B$15 -> 253.86489 | E27: =($D$7+SUMPRODUCT(($C$7:$C$12-$A27*$D$7:$D$12)/(1+$A27)^$B$7:$B$12)+($C$12*(1+E$25)-$A27*$D$13)/($A27-E$25)/(1+$A27)^6)/$B$15 -> 279.33316
A28: 0.085 | B28: =($D$7+SUMPRODUCT(($C$7:$C$12-$A28*$D$7:$D$12)/(1+$A28)^$B$7:$B$12)+($C$12*(1+B$25)-$A28*$D$13)/($A28-B$25)/(1+$A28)^6)/$B$15 -> 197.95995 | C28: =($D$7+SUMPRODUCT(($C$7:$C$12-$A28*$D$7:$D$12)/(1+$A28)^$B$7:$B$12)+($C$12*(1+C$25)-$A28*$D$13)/($A28-C$25)/(1+$A28)^6)/$B$15 -> 211.47351 | D28: =($D$7+SUMPRODUCT(($C$7:$C$12-$A28*$D$7:$D$12)/(1+$A28)^$B$7:$B$12)+($C$12*(1+D$25)-$A28*$D$13)/($A28-D$25)/(1+$A28)^6)/$B$15 -> 227.68978 | E28: =($D$7+SUMPRODUCT(($C$7:$C$12-$A28*$D$7:$D$12)/(1+$A28)^$B$7:$B$12)+($C$12*(1+E$25)-$A28*$D$13)/($A28-E$25)/(1+$A28)^6)/$B$15 -> 247.50966
A30: Base case range (CoE 7.5% to 8.5%, g 2.5% to 3.5%): low | B30: =MIN(B26:D28) -> 197.95995
A31: Base case range: high | B31: =MAX(B26:D28) -> 286.60699
A32: Bull case (CoE 8%, g 4%) | B32: =E27 -> 279.33316 | C32: =B32/$B$16-1 -> -0.1608845
A33: Value added by raising g from 3% to 4% at CoE 8% | B33: =E27-C27 -> 45.842888
A35: 4. Market implied assumptions (solved with Goal Seek: value = market price)
A36: Item | B36: Implied rate | C36: Value at implied rate | D36: Market price | E36: Difference
A37: Implied terminal growth at CoE 8% | B37: 0.04757597 | C37: =($D$7+SUMPRODUCT(($C$7:$C$12-$B$17*$D$7:$D$12)/(1+$B$17)^$B$7:$B$12)+($C$12*(1+B37)-$B$17*$D$13)/($B$17-B37)/(1+$B$17)^6)/$B$15 -> 332.88979 | D37: =$B$16 -> 332.89 | E37: =C37-D37 -> -0.00021272347
A38: Implied cost of equity at g 3% | B38: 0.065467658 | C38: =($D$7+SUMPRODUCT(($C$7:$C$12-B38*$D$7:$D$12)/(1+B38)^$B$7:$B$12)+($C$12*(1+$B$18)-B38*$D$13)/(B38-$B$18)/(1+B38)^6)/$B$15 -> 332.8898 | D38: =$B$16 -> 332.89 | E38: =C38-D38 -> -0.00020090685
A39: Growth increase needed (percentage points) | B39: =(B37-B18)*100 -> 1.757597
A40: Cost of equity decrease needed (percentage points) | B40: =(B17-B38)*100 -> 1.4532342
A42: 5. CAPM check of the cost of equity
A43: 10 year Treasury yield, nominal, 5 Oct 2026 | B43: 0.0531 | C43: FRED series DGS10
A44: Apple beta (5 year monthly) | B44: 1.07 | C44: Yahoo Finance key statistics, accessed 19 Oct 2026
A45: Implied equity risk premium, 1 Oct 2026 (headline) | B45: 0.042 | C45: Damodaran, ERPbymonth.xlsx, T12m with sustainable payout
A46: CAPM cost of equity | B46: =B43+B44*B45 -> 0.09804
A47: Value per share at CAPM cost of equity and g 3% | B47: =($D$7+SUMPRODUCT(($C$7:$C$12-$B$46*$D$7:$D$12)/(1+$B$46)^$B$7:$B$12)+($C$12*(1+$B$18)-$B$46*$D$13)/($B$46-$B$18)/(1+$B$46)^6)/$B$15 -> 169.34595 | C47: =B47/$B$16-1 -> -0.49128557
A49: Damodaran ERP version, 1 Oct 2026 | B49: ERP | C49: CAPM cost of equity
A50: T12m with sustainable payout (headline) | B50: 0.042 | C50: =$B$43+$B$44*B50 -> 0.09804
A51: T12m | B51: 0.037 | C51: =$B$43+$B$44*B51 -> 0.09269
A52: T12m with adjusted riskfree rate | B52: 0.0392 | C52: =$B$43+$B$44*B52 -> 0.095044
A53: Smoothed | B53: 0.0567 | C53: =$B$43+$B$44*B53 -> 0.113769
A54: ERP needed for CAPM to equal the given cost of equity | B54: =($B$17-$B$43)/$B$44 -> 0.025140187
A55: ERP needed for CAPM to equal the implied cost of equity | B55: =($B$38-$B$43)/$B$44 -> 0.011558559
A57: 6. Long run nominal growth of the US economy vs terminal growth
A58: 10 year Treasury yield, inflation indexed, 5 Oct 2026 | B58: 0.0295 | C58: FRED series DFII10
A59: Expected inflation (breakeven) | B59: =B43-B58 -> 0.0236
A60: Longer run real GDP growth, FOMC median, 16 Sep 2026 | B60: 0.02 | C60: FRED series GDPC1MDLR
A61: Long run nominal growth of the economy | B61: =(1+B60)*(1+B59)-1 -> 0.044072
A62: Group terminal growth minus economy growth | B62: =B18-B61 -> -0.014072
A63: Market implied growth minus economy growth | B63: =B37-B61 -> 0.0035039702
A65: 7. Relative valuation with and without Apple's historical premium (linked to J Relative Valuation)
A66: Peer median forward P/E | B66: ='J Relative Valuation'!C11 -> 22.97
A67: Peer median EV/EBIT | B67: ='J Relative Valuation'!D11 -> 21.91
A68: 5 year average P/E premium | B68: ='J Relative Valuation'!D19 -> 0.5741838
A69: 5 year average EV/EBIT premium | B69: ='J Relative Valuation'!G19 -> 0.41900768
A70: FY2027 net income | B70: ='J Relative Valuation'!B22 -> 145364.77
A71: FY2027 diluted shares (million) | B71: ='J Relative Valuation'!B23 -> 14430.723
A72: FY2026 EBIT | B72: ='J Relative Valuation'!B29 -> 156934.91
A73: FY2026 cash and securities less debt | B73: ='G Annual BS Forecast'!B7+'G Annual BS Forecast'!B8+'G Annual BS Forecast'!B16-'G Annual BS Forecast'!B27-'G Annual BS Forecast'!B28-'G Annual BS Forecast'!B31 -> 51857.981 | C73: Same items as J Relative Valuation B30
A75: Method | B75: With premium | C75: vs market | D75: Without premium | E75: vs market
A76: Forward P/E (FY2027 earnings) | B76: =$B$66*(1+$B$68)*$B$70/$B$71 -> 364.2399 | C76: =B76/$B$16-1 -> 0.094174953 | D76: =$B$66*$B$70/$B$71 -> 231.38334 | E76: =D76/$B$16-1 -> -0.30492554
A77: EV/EBIT (FY2026 EBIT) | B77: =($B$67*(1+$B$69)*$B$72+$B$73)/$B$15 -> 336.5895 | C77: =B77/$B$16-1 -> 0.011113293 | D77: =($B$67*$B$72+$B$73)/$B$15 -> 238.24586 | E77: =D77/$B$16-1 -> -0.28431055
A78: FTE / RI, for reference | B78: =B21 -> 233.49027 | C78: =B22 -> -0.29859632 | D78: =B21 -> 233.49027 | E78: =B22 -> -0.29859632
A79: Check: with premium values equal J Relative Valuation B26 and B31 | B79: =B76-'J Relative Valuation'!B26 -> 0 | C79: =B77-'J Relative Valuation'!B31 -> 0
A81: 8. Market multiples vs Apple's own history
A82: AAPL quoted forward P/E, Oct 2026 | B82: ='K Valuation Summary'!B22 -> 36.17
A83: AAPL average forward P/E, 2021 to 2025 | B83: =AVERAGE('J Relative Valuation'!B14:B18) -> 29.704
A85: 9. External benchmarks (reality check of forecasts)
A86: Metric | B86: Group model | C86: Benchmark | D86: Source | E86: Difference
A87: FY2026 revenue (USD bn) | B87: ='C2 Annual IS Forecast'!G9/1000 -> 477.52102 | C87: 477.9 | D87: LSEG I/B/E/S mean, 2 Oct 2026 | E87: =B87/C87-1 -> -0.00079301109
A88: FY2026 diluted EPS (USD) | B88: ='C2 Annual IS Forecast'!G33 -> 8.8668361 | C88: 8.859 | D88: LSEG I/B/E/S mean, 2 Oct 2026 | E88: =B88/C88-1 -> 0.00088454052
A89: FY2027 revenue (USD bn) | B89: ='C2 Annual IS Forecast'!H9/1000 -> 517.43774 | C89: 527.1 | D89: LSEG I/B/E/S mean, 2 Oct 2026 | E89: =B89/C89-1 -> -0.018330976
A90: FY2027 diluted EPS (USD) | B90: ='C2 Annual IS Forecast'!H33 -> 10.073284 | C90: 9.625 | D90: LSEG I/B/E/S mean, 2 Oct 2026 | E90: =B90/C90-1 -> 0.046574974
A91: Revenue CAGR FY2025 to FY2030 | B91: =('C2 Annual IS Forecast'!K9/'C2 Annual IS Forecast'!B9)^(1/5)-1 -> 0.084781437 | C91: 0.09 | D91: Morningstar, 7 Aug 2026 | E91: =B91-C91 -> -0.0052185629
A92: FY2025 iPhone revenue, actual (USD m) | B92: 209586 | C92: Apple FY2025 Form 10-K
A93: iPhone revenue CAGR FY2025 to FY2030 | B93: =('C1 Revenue Build'!F18/B92)^(1/5)-1 -> 0.089405705 | C93: 0.1 | D93: Morningstar, 7 Aug 2026 | E93: =B93-C93 -> -0.010594295
A94: Morningstar fair value (USD) | C94: 290 | D94: Morningstar, 9 Sep 2026 | E94: =C94/$B$16-1 -> -0.12884136
A95: LSEG 12 month mean target (USD), range $215 to $405 | C95: 324.89 | D95: LSEG, 2 Oct 2026, 37 analysts | E95: =C95/$B$16-1 -> -0.024031963
A97: 10. Value of one percentage point of product gross margin (approximation)
A98: Tax rate (management guidance) | B98: ='D IS Assumptions'!I12 -> 0.165
A99: Fiscal year | B99: t | C99: Products revenue | D99: After-tax effect of 1 pp | E99: Present value
A100: FY2027 | B100: 1 | C100: ='C1 Revenue Build'!C23 -> 378638.38 | D100: =0.01*C100*(1-$B$98) -> 3161.6305 | E100: =D100/(1+$B$17)^B100 -> 2927.4356
A101: FY2028 | B101: 2 | C101: ='C1 Revenue Build'!D23 -> 400881.35 | D101: =0.01*C101*(1-$B$98) -> 3347.3593 | E101: =D101/(1+$B$17)^B101 -> 2869.821
A102: FY2029 | B102: 3 | C102: ='C1 Revenue Build'!E23 -> 421171.32 | D102: =0.01*C102*(1-$B$98) -> 3516.7805 | E102: =D102/(1+$B$17)^B102 -> 2791.7337
A103: FY2030 | B103: 4 | C103: ='C1 Revenue Build'!F23 -> 440406.58 | D103: =0.01*C103*(1-$B$98) -> 3677.3949 | E103: =D103/(1+$B$17)^B103 -> 2702.995
A104: FY2031 | B104: 5 | C104: ='C1 Revenue Build'!G23 -> 458717.41 | D104: =0.01*C104*(1-$B$98) -> 3830.2903 | E104: =D104/(1+$B$17)^B104 -> 2606.8312
A105: FY2032 | B105: 6 | C105: ='C1 Revenue Build'!H23 -> 475512.26 | D105: =0.01*C105*(1-$B$98) -> 3970.5274 | E105: =D105/(1+$B$17)^B105 -> 2502.1058
A106: Terminal value effect | E106: =D105*(1+$B$18)/($B$17-$B$18)/(1+$B$17)^6 -> 51543.379
A107: Value per share of 1 pp of product gross margin | B107: =SUM(E100:E106)/$B$15 -> 4.6378363
A108: Gap between market price and FTE / RI value per share | B108: =B16-B21 -> 99.39973
A109: Points of product gross margin needed to close the gap | B109: =B108/B107 -> 21.43235
A110: Approximation: assumes the extra after-tax profit is distributed, so book equity is unchanged.

Sheet M ROE and Ratios
A1: M. Q3 ROE, Q4 advanced DuPont analysis, and forecast turnover and leverage ratios (Q6b)
A2: Black = formula; green = link to another worksheet in this file. FY2025 figures come from the Form 10-K via C2 Annual IS Forecast (column B) and B Balance Sheet (column B). USD millions unless stated.
A4: 1. Q3 Return on common shareholders' equity, FY2025 (ending equity)
A5: Net income, FY2025 | B5: ='C2 Annual IS Forecast'!B30 -> 112010
A6: Total shareholders' equity, 27 Sep 2025 (no preferred stock, so equals common equity) | B6: ='B Balance Sheet'!B39 -> 73733
A7: ROE = net income / ending common equity | B7: =B5/B6 -> 1.5191298
A9: 2. Q4 Separation of operating and financial items, 27 Sep 2025
A10: Total assets | B10: ='B Balance Sheet'!B21 -> 359241
A11: Cash and cash equivalents | B11: ='B Balance Sheet'!B7 -> 35934
A12: Current marketable securities | B12: ='B Balance Sheet'!B8 -> 18763
A13: Non-current marketable securities | B13: ='B Balance Sheet'!B16 -> 77723
A14: Financial assets | B14: =SUM(B11:B13) -> 132420
A15: Operating assets | B15: =B10-B14 -> 226821
A16: Total liabilities | B16: ='B Balance Sheet'!B34 -> 285508
A17: Commercial paper | B17: ='B Balance Sheet'!B27 -> 7979
A18: Term debt, current | B18: ='B Balance Sheet'!B28 -> 12350
A19: Term debt, non-current | B19: ='B Balance Sheet'!B31 -> 78328
A20: Financial obligations | B20: =SUM(B17:B19) -> 98657
A21: Operating liabilities | B21: =B16-B20 -> 186851
A22: Net operating assets (NOA) | B22: =B15-B21 -> 39970
A23: Net financial obligations (NFO) | B23: =B20-B14 -> -33763
A24: Check: NOA - NFO - common equity (should be zero) | B24: =B22-B23-B6 -> 0
A26: 3. Q4 Advanced DuPont: ROE = RNOA + FLEV x Spread
A27: Operating income, FY2025 | B27: ='C2 Annual IS Forecast'!B22 -> 133050
A28: Effective tax rate, FY2025 (as reported in the Form 10-K) | B28: 0.156 | C28: Unrounded rate in C2 Annual IS Forecast B28 is 15.61%
A29: NOPAT = operating income x (1 - tax rate) | B29: =B27*(1-B28) -> 112294.2
A30: RNOA = NOPAT / NOA | B30: =B29/B22 -> 2.8094621
A31: FLEV = NFO / common equity | B31: =B23/B6 -> -0.45790894
A32: Implied net financial expense after tax = NOPAT - net income | B32: =B29-B5 -> 284.2
A33: Net borrowing cost (NBC) = net financial expense / NFO | B33: =B32/B23 -> -0.0084174984
A34: Spread = RNOA - NBC | B34: =B30-B33 -> 2.8178796
A35: ROE = RNOA + FLEV x Spread | B35: =B30+B31*B34 -> 1.5191298
A36: Check: difference from ROE in section 1 | B36: =B35-B7 -> 0
A38: 4. Q4 Margin analysis, FY2025
A39: Net sales | B39: ='C2 Annual IS Forecast'!B9 -> 416161
A40: Gross margin | B40: ='C2 Annual IS Forecast'!B14 -> 0.46905164
A41: Products gross margin | B41: ='C2 Annual IS Forecast'!B15 -> 0.3677065
A42: Services gross margin | B42: ='C2 Annual IS Forecast'!B16 -> 0.75408124
A43: R&D / net sales | B43: ='C2 Annual IS Forecast'!B19/'C2 Annual IS Forecast'!B9 -> 0.083020754
A44: SG&A / net sales | B44: ='C2 Annual IS Forecast'!B20/'C2 Annual IS Forecast'!B9 -> 0.066322889
A45: Operating margin | B45: ='C2 Annual IS Forecast'!B22/'C2 Annual IS Forecast'!B9 -> 0.319708
A46: NOPAT margin = NOPAT / net sales | B46: =B29/B39 -> 0.26983355
A47: Net profit margin | B47: ='C2 Annual IS Forecast'!B30/'C2 Annual IS Forecast'!B9 -> 0.26915064
A49: 5. Q4 Turnover analysis, FY2025 (year-end balances)
A50: NOA turnover = net sales / NOA | B50: =B39/B22 -> 10.411834
A51: Accounts receivable turnover = net sales / A/R | B51: =B39/'B Balance Sheet'!B9 -> 10.462353
A52: Inventory turnover = cost of sales / inventories | B52: ='C2 Annual IS Forecast'!B12/'B Balance Sheet'!B11 -> 38.642882
A53: Accounts payable turnover = cost of sales / A/P | B53: ='C2 Annual IS Forecast'!B12/'B Balance Sheet'!B24 -> 3.1628972
A54: PP&E turnover = net sales / net PP&E | B54: =B39/'B Balance Sheet'!B17 -> 8.3509451
A55: Total asset turnover = net sales / total assets | B55: =B39/B10 -> 1.1584452
A56: Operating liabilities / operating assets | B56: =B21/B15 -> 0.82378175
A57: Check: NOPAT margin x NOA turnover - RNOA (should be zero) | B57: =B46*B50-B30 -> 0
A59: 6. Q6b Forecast turnover and leverage ratios on year-end balances (linked to C2 Annual IS Forecast and G Annual BS Forecast)
A60: Ratio | B60: FY2026 | C60: FY2027 | D60: FY2028 | E60: FY2029 | F60: FY2030 | G60: FY2031 | H60: FY2032
A61: A/R turnover (net sales / A/R) | B61: ='C2 Annual IS Forecast'!G9/'G Annual BS Forecast'!B9 -> 10.870059 | C61: ='C2 Annual IS Forecast'!H9/'G Annual BS Forecast'!C9 -> 10.870059 | D61: ='C2 Annual IS Forecast'!I9/'G Annual BS Forecast'!D9 -> 10.870059 | E61: ='C2 Annual IS Forecast'!J9/'G Annual BS Forecast'!E9 -> 10.870059 | F61: ='C2 Annual IS Forecast'!K9/'G Annual BS Forecast'!F9 -> 10.870059 | G61: ='C2 Annual IS Forecast'!L9/'G Annual BS Forecast'!G9 -> 10.870059 | H61: ='C2 Annual IS Forecast'!M9/'G Annual BS Forecast'!H9 -> 10.870059
A62: Inventory turnover (cost of sales / inventories) | B62: ='C2 Annual IS Forecast'!G12/'G Annual BS Forecast'!B11 -> 20.315628 | C62: ='C2 Annual IS Forecast'!H12/'G Annual BS Forecast'!C11 -> 20.315628 | D62: ='C2 Annual IS Forecast'!I12/'G Annual BS Forecast'!D11 -> 20.315628 | E62: ='C2 Annual IS Forecast'!J12/'G Annual BS Forecast'!E11 -> 20.315628 | F62: ='C2 Annual IS Forecast'!K12/'G Annual BS Forecast'!F11 -> 20.315628 | G62: ='C2 Annual IS Forecast'!L12/'G Annual BS Forecast'!G11 -> 20.315628 | H62: ='C2 Annual IS Forecast'!M12/'G Annual BS Forecast'!H11 -> 20.315628
A63: A/P turnover (cost of sales / A/P) | B63: ='C2 Annual IS Forecast'!G12/'G Annual BS Forecast'!B24 -> 3.1947959 | C63: ='C2 Annual IS Forecast'!H12/'G Annual BS Forecast'!C24 -> 3.1947959 | D63: ='C2 Annual IS Forecast'!I12/'G Annual BS Forecast'!D24 -> 3.1947959 | E63: ='C2 Annual IS Forecast'!J12/'G Annual BS Forecast'!E24 -> 3.1947959 | F63: ='C2 Annual IS Forecast'!K12/'G Annual BS Forecast'!F24 -> 3.1947959 | G63: ='C2 Annual IS Forecast'!L12/'G Annual BS Forecast'!G24 -> 3.1947959 | H63: ='C2 Annual IS Forecast'!M12/'G Annual BS Forecast'!H24 -> 3.1947959
A64: Net operating assets | B64: =('G Annual BS Forecast'!B21-'G Annual BS Forecast'!B7-'G Annual BS Forecast'!B8-'G Annual BS Forecast'!B16)-('G Annual BS Forecast'!B34-'G Annual BS Forecast'!B27-'G Annual BS Forecast'!B28-'G Annual BS Forecast'!B31) -> 55137.198 | C64: =('G Annual BS Forecast'!C21-'G Annual BS Forecast'!C7-'G Annual BS Forecast'!C8-'G Annual BS Forecast'!C16)-('G Annual BS Forecast'!C34-'G Annual BS Forecast'!C27-'G Annual BS Forecast'!C28-'G Annual BS Forecast'!C31) -> 60072.801 | D64: =('G Annual BS Forecast'!D21-'G Annual BS Forecast'!D7-'G Annual BS Forecast'!D8-'G Annual BS Forecast'!D16)-('G Annual BS Forecast'!D34-'G Annual BS Forecast'!D27-'G Annual BS Forecast'!D28-'G Annual BS Forecast'!D31) -> 64757.675 | E64: =('G Annual BS Forecast'!E21-'G Annual BS Forecast'!E7-'G Annual BS Forecast'!E8-'G Annual BS Forecast'!E16)-('G Annual BS Forecast'!E34-'G Annual BS Forecast'!E27-'G Annual BS Forecast'!E28-'G Annual BS Forecast'!E31) -> 69271.244 | F64: =('G Annual BS Forecast'!F21-'G Annual BS Forecast'!F7-'G Annual BS Forecast'!F8-'G Annual BS Forecast'!F16)-('G Annual BS Forecast'!F34-'G Annual BS Forecast'!F27-'G Annual BS Forecast'!F28-'G Annual BS Forecast'!F31) -> 73663.776 | G64: =('G Annual BS Forecast'!G21-'G Annual BS Forecast'!G7-'G Annual BS Forecast'!G8-'G Annual BS Forecast'!G16)-('G Annual BS Forecast'!G34-'G Annual BS Forecast'!G27-'G Annual BS Forecast'!G28-'G Annual BS Forecast'!G31) -> 77900.999 | H64: =('G Annual BS Forecast'!H21-'G Annual BS Forecast'!H7-'G Annual BS Forecast'!H8-'G Annual BS Forecast'!H16)-('G Annual BS Forecast'!H34-'G Annual BS Forecast'!H27-'G Annual BS Forecast'!H28-'G Annual BS Forecast'!H31) -> 81844.959
A65: NOA turnover (net sales / NOA) | B65: ='C2 Annual IS Forecast'!G9/B64 -> 8.6605964 | C65: ='C2 Annual IS Forecast'!H9/C64 -> 8.6135112 | D65: ='C2 Annual IS Forecast'!I9/D64 -> 8.5696195 | E65: ='C2 Annual IS Forecast'!J9/E64 -> 8.5265589 | F65: ='C2 Annual IS Forecast'!K9/F64 -> 8.4863048 | G65: ='C2 Annual IS Forecast'!L9/G64 -> 8.4494708 | H65: ='C2 Annual IS Forecast'!M9/H64 -> 8.4181412
A66: RNOA (NOPAT / ending NOA) | B66: ='C2 Annual IS Forecast'!G22*(1-'C2 Annual IS Forecast'!G28)/B64 -> 2.3527319 | C66: ='C2 Annual IS Forecast'!H22*(1-'C2 Annual IS Forecast'!H28)/C64 -> 2.4054256 | D66: ='C2 Annual IS Forecast'!I22*(1-'C2 Annual IS Forecast'!I28)/D64 -> 2.4444394 | E66: ='C2 Annual IS Forecast'!J22*(1-'C2 Annual IS Forecast'!J28)/E64 -> 2.4828416 | F66: ='C2 Annual IS Forecast'!K22*(1-'C2 Annual IS Forecast'!K28)/F64 -> 2.5195345 | G66: ='C2 Annual IS Forecast'!L22*(1-'C2 Annual IS Forecast'!L28)/G64 -> 2.5541909 | H66: ='C2 Annual IS Forecast'!M22*(1-'C2 Annual IS Forecast'!M28)/H64 -> 2.5856725
A67: Interest-bearing debt / equity | B67: =('G Annual BS Forecast'!B27+'G Annual BS Forecast'!B28+'G Annual BS Forecast'!B31)/'G Annual BS Forecast'!B39 -> 0.7882972 | C67: =('G Annual BS Forecast'!C27+'G Annual BS Forecast'!C28+'G Annual BS Forecast'!C31)/'G Annual BS Forecast'!C39 -> 0.65010724 | D67: =('G Annual BS Forecast'!D27+'G Annual BS Forecast'!D28+'G Annual BS Forecast'!D31)/'G Annual BS Forecast'!D39 -> 0.5523148 | E67: =('G Annual BS Forecast'!E27+'G Annual BS Forecast'!E28+'G Annual BS Forecast'!E31)/'G Annual BS Forecast'!E39 -> 0.4788385 | F67: =('G Annual BS Forecast'!F27+'G Annual BS Forecast'!F28+'G Annual BS Forecast'!F31)/'G Annual BS Forecast'!F39 -> 0.42114657 | G67: =('G Annual BS Forecast'!G27+'G Annual BS Forecast'!G28+'G Annual BS Forecast'!G31)/'G Annual BS Forecast'!G39 -> 0.37486288 | H67: =('G Annual BS Forecast'!H27+'G Annual BS Forecast'!H28+'G Annual BS Forecast'!H31)/'G Annual BS Forecast'!H39 -> 0.33759925
A68: FLEV (NFO / equity) | B68: =(('G Annual BS Forecast'!B27+'G Annual BS Forecast'!B28+'G Annual BS Forecast'!B31)-('G Annual BS Forecast'!B7+'G Annual BS Forecast'!B8+'G Annual BS Forecast'!B16))/'G Annual BS Forecast'!B39 -> -0.48467587 | C68: =(('G Annual BS Forecast'!C27+'G Annual BS Forecast'!C28+'G Annual BS Forecast'!C31)-('G Annual BS Forecast'!C7+'G Annual BS Forecast'!C8+'G Annual BS Forecast'!C16))/'G Annual BS Forecast'!C39 -> -0.52264997 | D68: =(('G Annual BS Forecast'!D27+'G Annual BS Forecast'!D28+'G Annual BS Forecast'!D31)-('G Annual BS Forecast'!D7+'G Annual BS Forecast'!D8+'G Annual BS Forecast'!D16))/'G Annual BS Forecast'!D39 -> -0.54930756 | E68: =(('G Annual BS Forecast'!E27+'G Annual BS Forecast'!E28+'G Annual BS Forecast'!E31)-('G Annual BS Forecast'!E7+'G Annual BS Forecast'!E8+'G Annual BS Forecast'!E16))/'G Annual BS Forecast'!E39 -> -0.56910381 | F68: =(('G Annual BS Forecast'!F27+'G Annual BS Forecast'!F28+'G Annual BS Forecast'!F31)-('G Annual BS Forecast'!F7+'G Annual BS Forecast'!F8+'G Annual BS Forecast'!F16))/'G Annual BS Forecast'!F39 -> -0.58452384 | G68: =(('G Annual BS Forecast'!G27+'G Annual BS Forecast'!G28+'G Annual BS Forecast'!G31)-('G Annual BS Forecast'!G7+'G Annual BS Forecast'!G8+'G Annual BS Forecast'!G16))/'G Annual BS Forecast'!G39 -> -0.59681663 | H68: =(('G Annual BS Forecast'!H27+'G Annual BS Forecast'!H28+'G Annual BS Forecast'!H31)-('G Annual BS Forecast'!H7+'G Annual BS Forecast'!H8+'G Annual BS Forecast'!H16))/'G Annual BS Forecast'!H39 -> -0.6067137
A70: FY2026 uses FY2026 full-year flows over the FY2026 Q4 forecast year-end balance, as in G Annual BS Forecast rows 58 to 61.
