Workbook

Sheet bs
B1: Total assets | H1: Total liabilities | N1: Total equity | T1: Advances from customers | Z1: Contract liabilities | AF1: Deferred income-current liabilities | AL1: Deferred income-Noncurrent liabilities | AR1: long-term debts | AX1: long-term bonds payables | BD1: short-term borrowings | BJ1: Non-current liabilities within one year | BP1: current assets | BV1: current liabilities | CB1: Account receivable | CH1: Inventory | CN1: contract assets
A2: year | B2: N-5 | C2: N-4 | D2: N-3 | E2: N-2 | F2: N-1 | G2: N | H2: N-5 | I2: N-4 | J2: N-3 | K2: N-2 | L2: N-1 | M2: N | N2: N-5 | O2: N-4 | P2: N-3 | Q2: N-2 | R2: N-1 | S2: N | T2: N-5 | U2: N-4 | V2: N-3 | W2: N-2 | X2: N-1 | Y2: N | Z2: N-5 | AA2: N-4 | AB2: N-3 | AC2: N-2 | AD2: N-1 | AE2: N | AF2: N-5 | AG2: N-4 | AH2: N-3 | AI2: N-2 | AJ2: N-1 | AK2: N | AL2: N-5 | AM2: N-4 | AN2: N-3 | AO2: N-2 | AP2: N-1 | AQ2: N | AR2: N-5 | AS2: N-4 | AT2: N-3 | AU2: N-2 | AV2: N-1 | AW2: N | AX2: N-5 | AY2: N-4 | AZ2: N-3 | BA2: N-2 | BB2: N-1 | BC2: N | BD2: N-5 | BE2: N-4 | BF2: N-3 | BG2: N-2 | BH2: N-1 | BI2: N | BJ2: N-5 | BK2: N-4 | BL2: N-3 | BM2: N-2 | BN2: N-1 | BO2: N | BP2: N-5 | BQ2: N-4 | BR2: N-3 | BS2: N-2 | BT2: N-1 | BU2: N | BV2: N-5 | BW2: N-4 | BX2: N-3 | BY2: N-2 | BZ2: N-1 | CA2: N | CB2: N-5 | CC2: N-4 | CD2: N-3 | CE2: N-2 | CF2: N-1 | CG2: N | CH2: N-5 | CI2: N-4 | CJ2: N-3 | CK2: N-2 | CL2: N-1 | CM2: N | CN2: N-5 | CO2: N-4 | CP2: N-3 | CQ2: N-2 | CR2: N-1 | CS2: N
B3: 2016 | C3: 2017 | D3: 2018 | E3: 2019 | F3: 2020 | G3: 2021 | H3: 2016 | I3: 2017 | J3: 2018 | K3: 2019 | L3: 2020 | M3: 2021 | N3: 2016 | O3: 2017 | P3: 2018 | Q3: 2019 | R3: 2020 | S3: 2021 | T3: 2016 | U3: 2017 | V3: 2018 | W3: 2019 | X3: 2020 | Y3: 2021 | Z3: 2016 | AA3: 2017 | AB3: 2018 | AC3: 2019 | AD3: 2020 | AE3: 2021 | AF3: 2016 | AG3: 2017 | AH3: 2018 | AI3: 2019 | AJ3: 2020 | AK3: 2021 | AL3: 2016 | AM3: 2017 | AN3: 2018 | AO3: 2019 | AP3: 2020 | AQ3: 2021 | AR3: 2016 | AS3: 2017 | AT3: 2018 | AU3: 2019 | AV3: 2020 | AW3: 2021 | AX3: 2016 | AY3: 2017 | AZ3: 2018 | BA3: 2019 | BB3: 2020 | BC3: 2021 | BD3: 2016 | BE3: 2017 | BF3: 2018 | BG3: 2019 | BH3: 2020 | BI3: 2021 | BJ3: 2016 | BK3: 2017 | BL3: 2018 | BM3: 2019 | BN3: 2020 | BO3: 2021 | BP3: 2016 | BQ3: 2017 | BR3: 2018 | BS3: 2019 | BT3: 2020 | BU3: 2021 | BV3: 2016 | BW3: 2017 | BX3: 2018 | BY3: 2019 | BZ3: 2020 | CA3: 2021 | CB3: 2016 | CC3: 2017 | CD3: 2018 | CE3: 2019 | CF3: 2020 | CG3: 2021 | CH3: 2016 | CI3: 2017 | CJ3: 2018 | CK3: 2019 | CL3: 2020 | CM3: 2021 | CN3: 2016 | CO3: 2017 | CP3: 2018 | CQ3: 2019 | CR3: 2020 | CS3: 2021
A4: stkcd
A5: 002564 | B5: 1.7004836e+10 | C5: 2.2586717e+10 | D5: 2.5864752e+10 | E5: 3.1826113e+10 | F5: 3.0387895e+10 | G5: 2.8472355e+10 | H5: 1.4224209e+10 | I5: 1.9426889e+10 | J5: 2.1507466e+10 | K5: 2.7327117e+10 | L5: 2.7301418e+10 | M5: 2.6235095e+10 | N5: 2.7806264e+09 | O5: 3.1598283e+09 | P5: 4.3572856e+09 | Q5: 4.4989964e+09 | R5: 3.0864771e+09 | S5: 2.2372606e+09 | T5: 6.7962335e+08 | U5: 2.5544019e+09 | V5: 2.3184933e+09 | W5: 0 | AC5: 3.3350259e+09 | AD5: 3.7133644e+09 | AE5: 2.3991572e+09 | AL5: 28334944 | AM5: 21674785 | AN5: 10448667 | AO5: 8245666.7 | AP5: 5042666.7 | AQ5: 3275000 | AR5: 2.0456948e+09 | AS5: 2.5194239e+09 | AT5: 6.6594997e+08 | AU5: 4.6298266e+09 | AV5: 4916500000 | AW5: 3730500000 | AX5: 4.4721607e+08 | BA5: 0 | BD5: 2.3983231e+09 | BE5: 3.0195183e+09 | BF5: 6847020000 | BG5: 6269244000 | BH5: 5.3057837e+09 | BI5: 4694800000 | BJ5: 1.478325e+09 | BK5: 1.8637561e+09 | BL5: 2.4371421e+09 | BM5: 1.3137038e+09 | BN5: 2.0264266e+09 | BO5: 4.2728304e+09 | BP5: 1.1960647e+10 | BQ5: 17454797991 | BR5: 1.9910884e+10 | BS5: 2.537087e+10 | BT5: 2.4328693e+10 | BU5: 2.2146279e+10 | BV5: 1.0159178e+10 | BW5: 1.5712893e+10 | BX5: 2.0106942e+10 | BY5: 2.2634928e+10 | BZ5: 2.2345065e+10 | CA5: 2.2473239e+10 | CB5: 3.6891334e+09 | CC5: 4.8452735e+09 | CD5: 7.4626518e+09 | CE5: 6.7934111e+09 | CF5: 6.23888e+09 | CG5: 4.5219054e+09 | CH5: 5.19858e+09 | CI5: 7.4392013e+09 | CJ5: 7.1135823e+09 | CK5: 2.9086657e+09 | CL5: 1.9140471e+09 | CM5: 1.8662541e+09 | CQ5: 7.9819345e+09 | CR5: 8.134965e+09 | CS5: 9.043458e+09
A6: 002584 | B6: 2.3725485e+09 | C6: 2.4829789e+09 | D6: 3.5092089e+09 | E6: 4.2309354e+09 | F6: 4.4806209e+09 | G6: 4.8104321e+09 | H6: 5.6204616e+08 | I6: 7.6056175e+08 | J6: 1.6920617e+09 | K6: 2.2314189e+09 | L6: 2.3911266e+09 | M6: 2.5040539e+09 | N6: 1.8105023e+09 | O6: 1.7248367e+09 | P6: 1.8171472e+09 | Q6: 1.9995165e+09 | R6: 2.0894943e+09 | S6: 2.3063782e+09 | T6: 32707870 | U6: 18738125 | V6: 52654799 | W6: 29759609 | X6: 27408 | AD6: 38342103 | AE6: 37012939 | AL6: 9262000 | AM6: 9980666.7 | AN6: 7365575.8 | AO6: 5250484.8 | AP6: 4035393.9 | AQ6: 2820303 | AR6: 27300000 | AS6: 47300000 | AT6: 270000000 | AU6: 217431172 | AV6: 142528000 | AW6: 47115737 | BD6: 98326154 | BE6: 2.2441514e+08 | BF6: 8.0637564e+08 | BG6: 1.0754602e+09 | BH6: 7.5238057e+08 | BI6: 5.1209557e+08 | BL6: 47300000 | BM6: 30612849 | BN6: 20367219 | BO6: 1.2137819e+08 | BP6: 1.3711811e+09 | BQ6: 1.5827072e+09 | BR6: 2.2653292e+09 | BS6: 2.9038586e+09 | BT6: 3.3967729e+09 | BU6: 3.6994889e+09 | BV6: 5.2548416e+08 | BW6: 7.0328108e+08 | BX6: 1.4119073e+09 | BY6: 1.976258e+09 | BZ6: 2.2100148e+09 | CA6: 2.3921345e+09 | CB6: 4.0210527e+08 | CC6: 3.757599e+08 | CD6: 7.0442621e+08 | CE6: 5.9584264e+08 | CF6: 1.1400484e+09 | CG6: 9.9162337e+08 | CH6: 3.2594781e+08 | CI6: 3.2410466e+08 | CJ6: 3.4898379e+08 | CK6: 3.9525623e+08 | CL6: 7.1333568e+08 | CM6: 4.5442446e+08
A7: 300044 | B7: 2.0770726e+09 | C7: 4.2944252e+09 | D7: 4.7925874e+09 | E7: 4.5958696e+09 | F7: 4.5826397e+09 | G7: 3.3201576e+09 | H7: 1.1707491e+09 | I7: 1.9608862e+09 | J7: 2.3737201e+09 | K7: 2.8469942e+09 | L7: 3.3274262e+09 | M7: 2.2830422e+09 | N7: 9.0632349e+08 | O7: 2.333539e+09 | P7: 2.4188673e+09 | Q7: 1.7488753e+09 | R7: 1.2552136e+09 | S7: 1.0371154e+09 | T7: 72286344 | U7: 1.6568973e+08 | V7: 1.2317702e+08 | W7: 1.8807787e+08 | X7: 648193.76 | Y7: 205230.2 | AD7: 1.3737411e+08 | AE7: 66047376 | AL7: 29169833 | AM7: 31540076 | AN7: 33404503 | AO7: 26684004 | AP7: 34833924 | AQ7: 28984781 | AS7: 146477451 | AT7: 438000000 | AU7: 5.7581967e+08 | AV7: 1.023044e+09 | AW7: 4.9623444e+08 | BD7: 434000000 | BE7: 835600000 | BF7: 835730000 | BG7: 9.2439127e+08 | BH7: 6.2935081e+08 | BI7: 3.24417e+08 | BL7: 37000000 | BM7: 58018987 | BN7: 1.2720276e+08 | BO7: 51672647 | BP7: 1.3133685e+09 | BQ7: 2.3435039e+09 | BR7: 2.4483146e+09 | BS7: 2.6208792e+09 | BT7: 2.245809e+09 | BU7: 2.209976e+09 | BV7: 1.1415793e+09 | BW7: 1.7813833e+09 | BX7: 1.90092e+09 | BY7: 2.0091261e+09 | BZ7: 2.0530359e+09 | CA7: 1.757655e+09 | CB7: 4.1647284e+08 | CC7: 5.8050967e+08 | CD7: 1.803745e+09 | CE7: 1.3759489e+09 | CF7: 5.9567162e+08 | CG7: 2.9686157e+08 | CH7: 5.4023766e+08 | CI7: 9.742558e+08 | CJ7: 87500365 | CK7: 1.2842103e+08 | CL7: 40628955 | CM7: 52962098 | CR7: 5.6556398e+08 | CS7: 2.084408e+08

Sheet is
B1: Net sales/Revenue | H1: Cost of goods sold | N1: Tax And Additional Fees Of Operations | T1: Selling expense | Z1: Administrative expense | AF1: R&D expense | AL1: Net profit
A2: year | B2: N-5 | C2: N-4 | D2: N-3 | E2: N-2 | F2: N-1 | G2: N | H2: N-5 | I2: N-4 | J2: N-3 | K2: N-2 | L2: N-1 | M2: N | N2: N-5 | O2: N-4 | P2: N-3 | Q2: N-2 | R2: N-1 | S2: N | T2: N-5 | U2: N-4 | V2: N-3 | W2: N-2 | X2: N-1 | Y2: N | Z2: N-5 | AA2: N-4 | AB2: N-3 | AC2: N-2 | AD2: N-1 | AE2: N | AF2: N-5 | AG2: N-4 | AH2: N-3 | AI2: N-2 | AJ2: N-1 | AK2: N | AL2: N-5 | AM2: N-4 | AN2: N-3 | AO2: N-2 | AP2: N-1 | AQ2: N
B3: 2016 | C3: 2017 | D3: 2018 | E3: 2019 | F3: 2020 | G3: 2021 | H3: 2016 | I3: 2017 | J3: 2018 | K3: 2019 | L3: 2020 | M3: 2021 | N3: 2016 | O3: 2017 | P3: 2018 | Q3: 2019 | R3: 2020 | S3: 2021 | T3: 2016 | U3: 2017 | V3: 2018 | W3: 2019 | X3: 2020 | Y3: 2021 | Z3: 2016 | AA3: 2017 | AB3: 2018 | AC3: 2019 | AD3: 2020 | AE3: 2021 | AF3: 2016 | AG3: 2017 | AH3: 2018 | AI3: 2019 | AJ3: 2020 | AK3: 2021 | AL3: 2016 | AM3: 2017 | AN3: 2018 | AO3: 2019 | AP3: 2020 | AQ3: 2021
A4: stkcd
A5: 002564 | B5: 1.1951452e+09 | C5: 1.0403684e+10 | D5: 7.7001635e+09 | E5: 1.0779197e+10 | F5: 7.7124736e+09 | G5: 6.8067912e+09 | H5: 9.7983838e+08 | I5: 9.2813995e+09 | J5: 6.5582098e+09 | K5: 9.2800606e+09 | L5: 7.6896156e+09 | M5: 5.6706337e+09 | N5: 20190136 | O5: 36205192 | P5: 26398820 | Q5: 31703523 | R5: 31857634 | S5: 30964087 | T5: 39772376 | U5: 89749952 | V5: 57561291 | W5: 67563388 | X5: 44459026 | Y5: 45204394 | Z5: 2.3282551e+08 | AA5: 3.2137726e+08 | AB5: 2.7620403e+08 | AC5: 2.5651067e+08 | AD5: 2.2701737e+08 | AE5: 1.9714701e+08 | AH5: 80886178 | AI5: 1.0032732e+08 | AJ5: 2.8492251e+08 | AK5: 2.4277138e+08 | AL5: -3.0589586e+08 | AM5: 3.2051663e+08 | AN5: 1.8548813e+08 | AO5: 1.3884024e+08 | AP5: -1.4019205e+09 | AQ5: -8.2324348e+08
A6: 002584 | B6: 2.9283835e+09 | C6: 3.3949898e+09 | D6: 3.3550784e+09 | E6: 3.337662e+09 | F6: 5.645523e+09 | G6: 5.3799036e+09 | H6: 2.4905021e+09 | I6: 2.9342481e+09 | J6: 2.8176085e+09 | K6: 2.805586e+09 | L6: 5.1677294e+09 | M6: 4.835965e+09 | N6: 11977186 | O6: 15715395 | P6: 13365956 | Q6: 13598069 | R6: 14084444 | S6: 16036144 | T6: 1.4376775e+08 | U6: 1.5648804e+08 | V6: 1.829836e+08 | W6: 1.8312515e+08 | X6: 1.2016726e+08 | Y6: 1.0863223e+08 | Z6: 1.6834551e+08 | AA6: 1.8916421e+08 | AB6: 1.2675202e+08 | AC6: 1.213106e+08 | AD6: 1.3130105e+08 | AE6: 1.3212815e+08 | AH6: 81745373 | AI6: 87580450 | AJ6: 1.0271916e+08 | AK6: 1.1896857e+08 | AL6: 90658054 | AM6: 84969400 | AN6: 63267754 | AO6: 34818626 | AP6: 65002428 | AQ6: 2.011198e+08
A7: 300044 | B7: 1.0020142e+09 | C7: 1.4984941e+09 | D7: 1.2950708e+09 | E7: 1.2550327e+09 | F7: 1.355424e+09 | G7: 1.0323947e+09 | H7: 8.3046644e+08 | I7: 1.1222505e+09 | J7: 8.2681308e+08 | K7: 8.8039867e+08 | L7: 9.1422401e+08 | M7: 8.1068932e+08 | N7: 3063133 | O7: 3876136.1 | P7: 4830112.2 | Q7: 4280898.6 | R7: 3457894 | S7: 5411206.8 | T7: 27483895 | U7: 40931403 | V7: 33840931 | W7: 63636563 | X7: 1.3739489e+08 | Y7: 64997506 | Z7: 79943663 | AA7: 1.2950525e+08 | AB7: 1.4967169e+08 | AC7: 1.4456016e+08 | AD7: 1.4459734e+08 | AE7: 1.393107e+08 | AI7: 61738522 | AJ7: 70712769 | AK7: 82124953 | AL7: 1.0272779e+08 | AM7: 1.803735e+08 | AN7: 99185266 | AO7: -4.8434976e+08 | AP7: -4.2918871e+08 | AQ7: -3.5486701e+08

Sheet cf
B1: Net Cash Flow From Operating Activities
A2: year | B2: N-5 | C2: N-4 | D2: N-3 | E2: N-2 | F2: N-1 | G2: N
B3: 2016 | C3: 2017 | D3: 2018 | E3: 2019 | F3: 2020 | G3: 2021
A4: stkcd
A5: 002564 | B5: 2.666199e+08 | C5: -5.0957237e+08 | D5: -2.3068256e+09 | E5: 2.0806497e+08 | F5: 49152731 | G5: -6.1548415e+08
A6: 002584 | B6: 11002036 | C6: -19245071 | D6: -97102373 | E6: 95892729 | F6: 44571222 | G6: 3.4661765e+08
A7: 300044 | B7: -79988568 | C7: -3.3903156e+08 | D7: 39212720 | E7: 3.6318613e+08 | F7: 24689960 | G7: 4.0841229e+08

Sheet ROE
A1: Dupont Analysis | B1: 2018 | C1: 2019 | D1: 2020 | E1: 2021 | F1: 2022
A2: ROE (Average Equity) | B2: N-4 | C2: N-3 | D2: N-2 | E2: N-1 | F2: N
A3: *ST天沃 | B3: =is!AM5/((bs!N5+bs!O5)/2) -> 0.1079098 | C3: =is!AN5/((bs!O5+bs!P5)/2) -> 0.049350888 | D3: =is!AO5/((bs!P5+bs!Q5)/2) -> 0.03135407 | E3: =is!AP5/((bs!Q5+bs!R5)/2) -> -0.36963295 | F3: =is!AQ5/((bs!R5+bs!S5)/2) -> -0.30927274
A4: 西陇科学 | B4: =is!AM6/((bs!N6+bs!O6)/2) -> 0.0480686 | C4: =is!AN6/((bs!O6+bs!P6)/2) -> 0.035724472 | D4: =is!AO6/((bs!P6+bs!Q6)/2) -> 0.018245582 | E4: =is!AP6/((bs!Q6+bs!R6)/2) -> 0.031793718 | F4: =is!AQ6/((bs!R6+bs!S6)/2) -> 0.091503927
A5: 赛为智能 | B5: =is!AM7/((bs!N7+bs!O7)/2) -> 0.11134639 | C5: =is!AN7/((bs!O7+bs!P7)/2) -> 0.041741072 | D5: =is!AO7/((bs!P7+bs!Q7)/2) -> -0.23242786 | E5: =is!AP7/((bs!Q7+bs!R7)/2) -> -0.28573636 | F5: =is!AQ7/((bs!R7+bs!S7)/2) -> -0.30961263
A6: Profit/Sales | B6: N-4 | C6: N-3 | D6: N-2 | E6: N-1 | F6: N
A7: *ST天沃 | B7: =is!AM5/is!C5 -> 0.030807995 | C7: =is!AN5/is!D5 -> 0.024088855 | D7: =is!AO5/is!E5 -> 0.012880388 | E7: =is!AP5/is!F5 -> -0.18177313 | F7: =is!AQ5/is!G5 -> -0.12094443
A8: 西陇科学 | B8: =is!AM6/is!C6 -> 0.025027881 | C8: =is!AN6/is!D6 -> 0.01885731 | D8: =is!AO6/is!E6 -> 0.010432041 | E8: =is!AP6/is!F6 -> 0.011513978 | F8: =is!AQ6/is!G6 -> 0.037383532
A9: 赛为智能 | B9: =is!AM7/is!C7 -> 0.12036984 | C9: =is!AN7/is!D7 -> 0.07658675 | D9: =is!AO7/is!E7 -> -0.38592603 | E9: =is!AP7/is!F7 -> -0.31664535 | F9: =is!AQ7/is!G7 -> -0.34373191
A10: Sales/Avearge Total assets | B10: N-4 | C10: N-3 | D10: N-2 | E10: N-1 | F10: N
A11: *ST天沃 | B11: =is!C5/((bs!B5+bs!C5)/2) -> 0.52555067 | C11: =is!D5/((bs!C5+bs!D5)/2) -> 0.31785057 | D11: =is!E5/((bs!D5+bs!E5)/2) -> 0.37368818 | E11: =is!F5/((bs!E5+bs!F5)/2) -> 0.24793367 | F11: =is!G5/((bs!F5+bs!G5)/2) -> 0.23128652
A12: 西陇科学 | B12: =is!C6/((bs!B6+bs!C6)/2) -> 1.3984021 | C12: =is!D6/((bs!C6+bs!D6)/2) -> 1.1198175 | D12: =is!E6/((bs!D6+bs!E6)/2) -> 0.86242888 | E12: =is!F6/((bs!E6+bs!F6)/2) -> 1.2960998 | F12: =is!G6/((bs!F6+bs!G6)/2) -> 1.1580826
A13: 赛为智能 | B13: =is!C7/((bs!B7+bs!C7)/2) -> 0.47037422 | C13: =is!D7/((bs!C7+bs!D7)/2) -> 0.28503775 | D13: =is!E7/((bs!D7+bs!E7)/2) -> 0.26735653 | E13: =is!F7/((bs!E7+bs!F7)/2) -> 0.29534731 | F13: =is!G7/((bs!F7+bs!G7)/2) -> 0.26127324
A14: Average Total assets /Average Total equity | B14: N-4 | C14: N-3 | D14: N-2 | E14: N-1 | F14: N
A15: *ST天沃 | B15: =((bs!B5+bs!C5)/2)/((bs!N5+bs!O5)/2) -> 6.6647344 | C15: =((bs!C5+bs!D5)/2)/((bs!O5+bs!P5)/2) -> 6.4454882 | D15: =((bs!D5+bs!E5)/2)/((bs!P5+bs!Q5)/2) -> 6.5141178 | E15: =((bs!E5+bs!F5)/2)/((bs!Q5+bs!R5)/2) -> 8.2017303 | F15: =((bs!F5+bs!G5)/2)/((bs!R5+bs!S5)/2) -> 11.056189
A16: 西陇科学 | B16: =((bs!B6+bs!C6)/2)/((bs!N6+bs!O6)/2) -> 1.3734262 | C16: =((bs!C6+bs!D6)/2)/((bs!O6+bs!P6)/2) -> 1.6917603 | D16: =((bs!D6+bs!E6)/2)/((bs!P6+bs!Q6)/2) -> 2.027987 | E16: =((bs!E6+bs!F6)/2)/((bs!Q6+bs!R6)/2) -> 2.1304801 | F16: =((bs!F6+bs!G6)/2)/((bs!R6+bs!S6)/2) -> 2.1135856
A17: 赛为智能 | B17: =((bs!B7+bs!C7)/2)/((bs!N7+bs!O7)/2) -> 1.9665951 | C17: =((bs!C7+bs!D7)/2)/((bs!O7+bs!P7)/2) -> 1.9120866 | D17: =((bs!D7+bs!E7)/2)/((bs!P7+bs!Q7)/2) -> 2.252648 | E17: =((bs!E7+bs!F7)/2)/((bs!Q7+bs!R7)/2) -> 3.0553388 | F17: =((bs!F7+bs!G7)/2)/((bs!R7+bs!S7)/2) -> 3.447497

Sheet Profitability
B1: 2018 | C1: 2019 | D1: 2020 | E1: 2021 | F1: 2022
A2: Gross Margin | B2: N-4 | C2: N-3 | D2: N-2 | E2: N-1 | F2: N
A3: *ST天沃 | B3: =(is!C5-is!I5)/is!C5 -> 0.10787372 | C3: =(is!D5-is!J5)/is!D5 -> 0.14830253 | D3: =(is!E5-is!K5)/is!E5 -> 0.13907682 | E3: =(is!F5-is!L5)/is!F5 -> 0.0029637612 | F3: =(is!G5-is!M5)/is!G5 -> 0.16691529
A4: 西陇科学 | B4: =(is!C6-is!I6)/is!C6 -> 0.13571226 | C4: =(is!D6-is!J6)/is!D6 -> 0.16019591 | D4: =(is!E6-is!K6)/is!E6 -> 0.15941578 | E4: =(is!F6-is!L6)/is!F6 -> 0.084632307 | F4: =(is!G6-is!M6)/is!G6 -> 0.10110564
A5: 赛为智能 | B5: =(is!C7-is!I7)/is!C7 -> 0.25108119 | C5: =(is!D7-is!J7)/is!D7 -> 0.36156922 | D5: =(is!E7-is!K7)/is!E7 -> 0.29850537 | E5: =(is!F7-is!L7)/is!F7 -> 0.32550701 | F5: =(is!G7-is!M7)/is!G7 -> 0.21474869
A6: Main Business Profit Margin | B6: N-4 | C6: N-3 | D6: N-2 | E6: N-1 | F6: N
A7: *ST天沃 | B7: =(is!C5-[1]Cis20!I5-is!O5-is!U5-is!AA5-is!AG5)/is!C5 -> #REF! | C7: =(is!D5-is!J5-is!P5-is!V5-is!AB5-is!AH5)/is!D5 -> 0.09102448 | D7: =(is!E5-is!K5-is!Q5-is!W5-is!AC5-is!AI5)/is!E5 -> 0.096763384 | E7: =(is!F5-is!L5-is!R5-is!X5-is!AD5-is!AJ5)/is!F5 -> -0.073309634 | F7: =(is!G5-is!M5-is!S5-is!Y5-is!AE5-is!AK5)/is!G5 -> 0.091095879
A8: 西陇科学 | B8: =(is!C6-is!I6-is!O6-is!U6-is!AA6-is!AG6)/is!C6 -> #VALUE! | C8: =(is!D6-is!J6-is!P6-is!V6-is!AB6-is!AH6)/is!D6 -> 0.039528996 | D8: =(is!E6-is!K6-is!Q6-is!W6-is!AC6-is!AI6)/is!E6 -> 0.03788931 | E8: =(is!F6-is!L6-is!R6-is!X6-is!AD6-is!AJ6)/is!F6 -> 0.019399747 | F8: =(is!G6-is!M6-is!S6-is!Y6-is!AE6-is!AK6)/is!G6 -> 0.031259572
A9: 赛为智能 | B9: =(is!C7-is!I7-is!O7-is!U7-is!AA7-is!AG7)/is!C7 -> #VALUE! | C9: =(is!D7-is!J7-is!P7-is!V7-is!AB7-is!AH7)/is!D7 -> #VALUE! | D9: =(is!E7-is!K7-is!Q7-is!W7-is!AC7-is!AI7)/is!E7 -> 0.080012136 | E9: =(is!F7-is!L7-is!R7-is!X7-is!AD7-is!AJ7)/is!F7 -> 0.062738392 | F9: =(is!G7-is!M7-is!S7-is!Y7-is!AE7-is!AK7)/is!G7 -> -0.067938105
A10: Profit Margin | B10: N-4 | C10: N-3 | D10: N-2 | E10: N-1 | F10: N
A11: *ST天沃 | B11: =is!AM5/is!C5 -> 0.030807995 | C11: =is!AN5/is!D5 -> 0.024088855 | D11: =is!AO5/is!E5 -> 0.012880388 | E11: =is!AP5/is!F5 -> -0.18177313 | F11: =is!AQ5/is!G5 -> -0.12094443
A12: 西陇科学 | B12: =is!AM6/is!C6 -> 0.025027881 | C12: =is!AN6/is!D6 -> 0.01885731 | D12: =is!AO6/is!E6 -> 0.010432041 | E12: =is!AP6/is!F6 -> 0.011513978 | F12: =is!AQ6/is!G6 -> 0.037383532
A13: 赛为智能 | B13: =is!AM7/is!C7 -> 0.12036984 | C13: =is!AN7/is!D7 -> 0.07658675 | D13: =is!AO7/is!E7 -> -0.38592603 | E13: =is!AP7/is!F7 -> -0.31664535 | F13: =is!AQ7/is!G7 -> -0.34373191

Sheet Reference1
A1: Net Sales
A2: - Cost of goods sold (Cost of sales)
A3: = Gross Profit
A4: - Selling, administrative, R&D expenses
A5: = Main business Profit
A6: + Investment income
A7: + Gains on changes in fair value of financial assets
A8: - Asset impairment losses
A9: +/(-) Gains/(Loss) on disposal of assets
A10: +/(-) Other income/(expense)
A11: = EBIT (Earnings before interest expense and taxes)
A12: -/(+) Net Financial expense/(income)
... A15: = Net profit

Sheet Reference2
A1: Non-interest bearing liabilitites
A2: + Interest-bearing liabililites (Total debt)
A3: = Total liabilities
A4: - Advances from customers/Contract liabilities
A5: - Deferred income
A6: = Total liabilities - Adjustment
A7: Long-term debt+ Short-term debt
A8: = Interest-bearing liabilities (Total debt)

Sheet Solvency_liquidity
B1: 2018 | C1: 2019 | D1: 2020 | E1: 2021 | F1: 2022
A2: Total liabilities (adjusted)/Total assets | B2: N-4 | C2: N-3 | D2: N-2 | E2: N-1 | F2: N
A3: *ST天沃 | B3: =(bs!I5-bs!U5-bs!AA5-bs!AH5-bs!AM5)/bs!C5 -> 0.74604964 | C3: =(bs!J5-bs!V5-bs!AB5-bs!AI5-bs!AN5)/bs!D5 -> 0.74149268 | D3: =(bs!K5-bs!W5-bs!AC5-bs!AJ5-bs!AO5)/bs!E5 -> 0.75359014 | E3: =(bs!L5-bs!X5-bs!AD5-bs!AK5-bs!AP5)/bs!F5 -> 0.77606596 | F3: =(bs!M5-bs!Y5-bs!AE5-bs!AL5-bs!AQ5)/bs!G5 -> 0.83605053
A4: 西陇科学 | B4: =(bs!I6-bs!U6-bs!AA6-bs!AH6-bs!AM6)/bs!C6 -> 0.29474393 | C4: =(bs!J6-bs!V6-bs!AB6-bs!AI6-bs!AN6)/bs!D6 -> 0.46507385 | D4: =(bs!K6-bs!W6-bs!AC6-bs!AJ6-bs!AO6)/bs!E6 -> 0.51913079 | E4: =(bs!L6-bs!X6-bs!AD6-bs!AK6-bs!AP6)/bs!F6 -> 0.52419558 | F4: =(bs!M6-bs!Y6-bs!AE6-bs!AL6-bs!AQ6)/bs!G6 -> 0.51034056
A5: 赛为智能 | B5: =(bs!I7-bs!U7-bs!AA7-bs!AH7-bs!AM7)/bs!C7 -> 0.41068509 | C5: =(bs!J7-bs!V7-bs!AB7-bs!AI7-bs!AN7)/bs!D7 -> 0.46261828 | D5: =(bs!K7-bs!W7-bs!AC7-bs!AJ7-bs!AO7)/bs!E7 -> 0.5727387 | E5: =(bs!L7-bs!X7-bs!AD7-bs!AK7-bs!AP7)/bs!F7 -> 0.68837398 | F5: =(bs!M7-bs!Y7-bs!AE7-bs!AL7-bs!AQ7)/bs!G7 -> 0.65016039
A6: Total debt/Total assets | B6: N-4 | C6: N-3 | D6: N-2 | E6: N-1 | F6: N
A7: *ST天沃 | B7: =(bs!AS5+bs!AY5+bs!BE5+bs!BK5)/bs!C5 -> 0.32774565 | C7: =(bs!AT5+bs!AZ5+bs!BF5+bs!BL5)/bs!D5 -> 0.38469776 | D7: =(bs!AU5+bs!BA5+bs!BG5+bs!BM5)/bs!E5 -> 0.3837344 | E7: =(bs!AV5+bs!BB5+bs!BH5+bs!BN5)/bs!F5 -> 0.4030786 | F7: =(bs!AW5+bs!BC5+bs!BI5+bs!BO5)/bs!G5 -> 0.44598103
A8: 西陇科学 | B8: =(bs!AS6+bs!AY6+bs!BE6+bs!BK6)/bs!C6 -> 0.10943111 | C8: =(bs!AT6+bs!AZ6+bs!BF6+bs!BL6)/bs!D6 -> 0.32020768 | D8: =(bs!AU6+bs!BA6+bs!BG6+bs!BM6)/bs!E6 -> 0.31281599 | E8: =(bs!AV6+bs!BB6+bs!BH6+bs!BN6)/bs!F6 -> 0.20427432 | F8: =(bs!AW6+bs!BC6+bs!BI6+bs!BO6)/bs!G6 -> 0.14148199
A9: 赛为智能 | B9: =(bs!AS7+bs!AY7+bs!BE7+bs!BK7)/bs!C7 -> 0.22868659 | C9: =(bs!AT7+bs!AZ7+bs!BF7+bs!BL7)/bs!D7 -> 0.2734911 | D9: =(bs!AU7+bs!BA7+bs!BG7+bs!BM7)/bs!E7 -> 0.33905008 | E9: =(bs!AV7+bs!BB7+bs!BH7+bs!BN7)/bs!F7 -> 0.3883346 | F9: =(bs!AW7+bs!BC7+bs!BI7+bs!BO7)/bs!G7 -> 0.26273574
A10: Current ratio | B10: N-4 | C10: N-3 | D10: N-2 | E10: N-1 | F10: N
A11: *ST天沃 | B11: =bs!BQ5/bs!BW5 -> 1.1108583 | C11: =bs!BR5/bs!BX5 -> 0.99024925 | D11: =bs!BS5/bs!BY5 -> 1.1208726 | E11: =bs!BT5/bs!BZ5 -> 1.0887725 | F11: =bs!BU5/bs!CA5 -> 0.98545117
A12: 西陇科学 | B12: =bs!BQ6/bs!BW6 -> 2.2504618 | C12: =bs!BR6/bs!BX6 -> 1.6044461 | D12: =bs!BS6/bs!BY6 -> 1.4693722 | E12: =bs!BT6/bs!BZ6 -> 1.536991 | F12: =bs!BU6/bs!CA6 -> 1.5465221
A13: 赛为智能 | B13: =bs!BQ7/bs!BW7 -> 1.3155528 | C13: =bs!BR7/bs!BX7 -> 1.287963 | D13: =bs!BS7/bs!BY7 -> 1.3044871 | E13: =bs!BT7/bs!BZ7 -> 1.0938966 | F13: =bs!BU7/bs!CA7 -> 1.2573435

Sheet Operation efficiency
B1: 2018 | C1: 2019 | D1: 2020 | E1: 2021 | F1: 2022
A2: Account receivables turnover ratio | B2: N-4 | C2: N-3 | D2: N-2 | E2: N-1 | F2: N
A3: *ST天沃 | B3: =is!C5/((bs!CB5+bs!CC5)/2) -> 2.4380566 | C3: =is!D5/((bs!CC5+bs!CD5)/2) -> 1.2512529 | D3: =is!E5/((bs!CD5+bs!CE5)/2) -> 1.5122264 | E3: =is!F5/((bs!CE5+bs!CF5)/2) -> 1.1835944 | F3: =is!G5/((bs!CF5+bs!CG5)/2) -> 1.2651105
A4: 西陇科学 | B4: =is!C6/((bs!CB6+bs!CC6)/2) -> 8.728993 | C4: =is!D6/((bs!CC6+bs!CD6)/2) -> 6.2120376 | D4: =is!E6/((bs!CD6+bs!CE6)/2) -> 5.1338028 | E4: =is!F6/((bs!CE6+bs!CF6)/2) -> 6.5044669 | F4: =is!G6/((bs!CF6+bs!CG6)/2) -> 5.0475909
A5: 赛为智能 | B5: =is!C7/((bs!CB7+bs!CC7)/2) -> 3.0060591 | C5: =is!D7/((bs!CC7+bs!CD7)/2) -> 1.0863528 | D5: =is!E7/((bs!CD7+bs!CE7)/2) -> 0.78940471 | E5: =is!F7/((bs!CE7+bs!CF7)/2) -> 1.374934 | F5: =is!G7/((bs!CF7+bs!CG7)/2) -> 2.3134036
A6: Days Sales Outstanding (DSO) | B6: N-4 | C6: N-3 | D6: N-2 | E6: N-1 | F6: N
A7: *ST天沃 | B7: =365/B3 -> 149.7094 | C7: =365/C3 -> 291.70762 | D7: =365/D3 -> 241.36598 | E7: =365/E3 -> 308.38266 | F7: =365/F3 -> 288.51235
A8: 西陇科学 | B8: =365/B4 -> 41.814674 | C8: =365/C4 -> 58.756889 | D8: =365/D4 -> 71.097393 | E8: =365/E4 -> 56.115283 | F8: =365/F4 -> 72.311724
A9: 赛为智能 | B9: =365/B5 -> 121.42143 | C9: =365/C5 -> 335.98662 | D9: =365/D5 -> 462.37373 | E9: =365/E5 -> 265.46729 | F9: =365/F5 -> 157.77619
A10: Inventory turnover ratio | B10: N-4 | C10: N-3 | D10: N-2 | E10: N-1 | F10: N
A11: *ST天沃 | B11: =is!I5/((bs!CH5+bs!CN5+bs!CI5+bs!CO5)/2) -> 1.4688337 | C11: =is!J5/((bs!CI5+bs!CO5+bs!CJ5+bs!CP5)/2) -> 0.9012997 | D11: =is!K5/((bs!CJ5+bs!CP5+bs!CK5+bs!CQ5)/2) -> 1.0308783 | E11: =is!L5/((bs!CK5+bs!CQ5+bs!CL5+bs!CR5)/2) -> 0.73445636 | F11: =is!M5/((bs!CL5+bs!CR5+bs!CM5+bs!CS5)/2) -> 0.54112394
A12: 西陇科学 | B12: =is!I6/((bs!CH6+bs!CN6+bs!CI6+bs!CO6)/2) -> 9.0277269 | C12: =is!J6/((bs!CI6+bs!CO6+bs!CJ6+bs!CP6)/2) -> 8.3721791 | D12: =is!K6/((bs!CJ6+bs!CP6+bs!CK6+bs!CQ6)/2) -> 7.5394655 | E12: =is!L6/((bs!CK6+bs!CQ6+bs!CL6+bs!CR6)/2) -> 9.3230509 | F12: =is!M6/((bs!CL6+bs!CR6+bs!CM6+bs!CS6)/2) -> 8.2824629
A13: 赛为智能 | B13: =is!I7/((bs!CH7+bs!CN7+bs!CI7+bs!CO7)/2) -> 1.4820143 | C13: =is!J7/((bs!CI7+bs!CO7+bs!CJ7+bs!CP7)/2) -> 1.5574444 | D13: =is!K7/((bs!CJ7+bs!CP7+bs!CK7+bs!CQ7)/2) -> 8.1548072 | E13: =is!L7/((bs!CK7+bs!CQ7+bs!CL7+bs!CR7)/2) -> 2.4889916 | F13: =is!M7/((bs!CL7+bs!CR7+bs!CM7+bs!CS7)/2) -> 1.8688179
A14: Days sales of inventory | B14: N-4 | C14: N-3 | D14: N-2 | E14: N-1 | F14: N
A15: *ST天沃 | B15: =365/B11 -> 248.49648 | C15: =365/C11 -> 404.97073 | D15: =365/D11 -> 354.06701 | E15: =365/E11 -> 496.96622 | F15: =365/F11 -> 674.522
A16: 西陇科学 | B16: =365/B12 -> 40.430997 | C16: =365/C12 -> 43.596774 | D16: =365/D12 -> 48.41192 | E16: =365/E12 -> 39.150274 | F16: =365/F12 -> 44.069017
A17: 赛为智能 | B17: =365/B13 -> 246.28643 | C17: =365/C13 -> 234.35829 | D17: =365/D13 -> 44.758876 | E17: =365/E13 -> 146.64573 | F17: =365/F13 -> 195.31063
